Workbook

Sheet progress
A1: A URL has been suggested for
A2: =COUNTA('glossaryterms-export'!G1:G1091) -> 888 | B2: entries,
A3: =A2/1091 -> 0.81393217 | B3: of the way to completion
A5: A URL has been determined for
A6: =COUNTA('glossaryterms-export'!H1:H1091) -> 712 | B6: entries,
A7: =A6/1091 -> 0.65261228 | B7: of the way to completion

Sheet PrioritizedGlossaryTerms
A1: Rank # | B1: https://www.adl.org/resources/backgrounder/764 | C1: Page path and screen class | D1: Redirected | E1: Regex to match main sheet | F1: Finalized But Not RD'd? | G1: Views | H1: Active users | I1: Views per active user | J1: Average engagement time per active user | K1: Event count
A2: 1 | B2: https://www.adl.org/resources/backgrounder/qanon | C2: /glossary/frazzledrip/ | E2: =_xlfn.REGEXREPLACE(C2, "(.*)\/$", "https://extremismterms.adl.org\1") -> https://extremismterms.adl.org/glossary/frazzledrip | F2: {=_xlfn.LET(_xlpm.rowNum,MATCH(E2,'glossaryterms-export'!C:C,0), IF(AND(NOT(ISBLANK(INDEX('glossaryterms-export'!H:H,_xlpm.rowNum))),ISBLANK(INDEX('glossaryterms-export'!I:I,_xlpm.rowNum))),"Ready to Fix",""))} | G2: 261350 | H2: 226953 | I2: 1.15156 | J2: 34.766313 | K2: 1045389 | L2: =VLOOKUP(H2,'PrioritizedGlossaryTerms'!A2:C1066
A3: 2 | B3: https://www.adl.org/resources/article/qanon-adherents-reeling-wake-inauguration-trump-departure | C3: /glossary/nesaragesara/ | D3: Y | E3: =_xlfn.REGEXREPLACE(C3, "(.*)\/$", "https://extremismterms.adl.org\1") -> https://extremismterms.adl.org/glossary/nesaragesara | F3: {=_xlfn.LET(_xlpm.rowNum,MATCH(E3,'glossaryterms-export'!C:C,0), IF(AND(NOT(ISBLANK(INDEX('glossaryterms-export'!H:H,_xlpm.rowNum))),ISBLANK(INDEX('glossaryterms-export'!I:I,_xlpm.rowNum))),"Ready to Fix",""))} | G3: 134513 | H3: 108466 | I3: 1.2401398 | J3: 42.681651 | K3: 549621
A4: 3 | C4: /glossary/europa-last-battle/ | E4: =_xlfn.REGEXREPLACE(C4, "(.*)\/$", "https://extremismterms.adl.org\1") -> https://extremismterms.adl.org/glossary/europa-last-battle | F4: {=_xlfn.LET(_xlpm.rowNum,MATCH(E4,'glossaryterms-export'!C:C,0), IF(AND(NOT(ISBLANK(INDEX('glossaryterms-export'!H:H,_xlpm.rowNum))),ISBLANK(INDEX('glossaryterms-export'!I:I,_xlpm.rowNum))),"Ready to Fix",""))} | G4: 56498 | H4: 49567 | I4: 1.1398309 | J4: 15.081324 | K4: 223938
A5: 4 | B5: https://www.adl.org/resources/backgrounder/incels-involuntary-celibates | C5: /glossary/foid/ | D5: Y | E5: =_xlfn.REGEXREPLACE(C5, "(.*)\/$", "https://extremismterms.adl.org\1") -> https://extremismterms.adl.org/glossary/foid | F5: {=_xlfn.LET(_xlpm.rowNum,MATCH(E5,'glossaryterms-export'!C:C,0), IF(AND(NOT(ISBLANK(INDEX('glossaryterms-export'!H:H,_xlpm.rowNum))),ISBLANK(INDEX('glossaryterms-export'!I:I,_xlpm.rowNum))),"Ready to Fix",""))} | G5: 38723 | H5: 33619 | I5: 1.1518189 | J5: 13.212648 | K5: 143337
A6: 5 | C6: /glossary/fall-cabal/ | E6: =_xlfn.REGEXREPLACE(C6, "(.*)\/$", "https://extremismterms.adl.org\1") -> https://extremismterms.adl.org/glossary/fall-cabal | F6: {=_xlfn.LET(_xlpm.rowNum,MATCH(E6,'glossaryterms-export'!C:C,0), IF(AND(NOT(ISBLANK(INDEX('glossaryterms-export'!H:H,_xlpm.rowNum))),ISBLANK(INDEX('glossaryterms-export'!I:I,_xlpm.rowNum))),"Ready to Fix",""))} | G6: 36024 | H6: 31002 | I6: 1.1619895 | J6: 18.501032 | K6: 145611
A7: 6 | B7: https://www.adl.org/resources/backgrounder/sovereign-citizen-movement-united-states | C7: /glossary/civil-peace-flagcivil-flag-peacetime/ | D7: Y | E7: =_xlfn.REGEXREPLACE(C7, "(.*)\/$", "https://extremismterms.adl.org\1") -> https://extremismterms.adl.org/glossary/civil-peace-flagcivil-flag-peacetime | F7: {=_xlfn.LET(_xlpm.rowNum,MATCH(E7,'glossaryterms-export'!C:C,0), IF(AND(NOT(ISBLANK(INDEX('glossaryterms-export'!H:H,_xlpm.rowNum))),ISBLANK(INDEX('glossaryterms-export'!I:I,_xlpm.rowNum))),"Ready to Fix",""))} | G7: 19701 | H7: 16924 | I7: 1.1640865 | J7: 28.443512 | K7: 71568
A8: 7 | B8: https://www.adl.org/resources/backgrounder/qanon | C8: /glossary/q-drop/ | D8: Y | E8: =_xlfn.REGEXREPLACE(C8, "(.*)\/$", "https://extremismterms.adl.org\1") -> https://extremismterms.adl.org/glossary/q-drop | F8: {=_xlfn.LET(_xlpm.rowNum,MATCH(E8,'glossaryterms-export'!C:C,0), IF(AND(NOT(ISBLANK(INDEX('glossaryterms-export'!H:H,_xlpm.rowNum))),ISBLANK(INDEX('glossaryterms-export'!I:I,_xlpm.rowNum))),"Ready to Fix",""))} | G8: 17973 | H8: 15317 | I8: 1.1734021 | J8: 14.664556 | K8: 72878
A9: 8 | B9: https://adl.org/resources/backgrounder/groyper-army-and-america-first | C9: /glossary/america-first/ | D9: Y | E9: =_xlfn.REGEXREPLACE(C9, "(.*)\/$", "https://extremismterms.adl.org\1") -> https://extremismterms.adl.org/glossary/america-first | F9: {=_xlfn.LET(_xlpm.rowNum,MATCH(E9,'glossaryterms-export'!C:C,0), IF(AND(NOT(ISBLANK(INDEX('glossaryterms-export'!H:H,_xlpm.rowNum))),ISBLANK(INDEX('glossaryterms-export'!I:I,_xlpm.rowNum))),"Ready to Fix",""))} | G9: 13745 | H9: 10547 | I9: 1.3032142 | J9: 22.075567 | K9: 49684
A10: 9 | B10: https://www.adl.org/resources/article/israel-hamas-ceasefire-sparks-fresh-wave-antisemitism-support-terror-us-anti | C10: /glossary/inverted-red-triangle/ | E10: =_xlfn.REGEXREPLACE(C10, "(.*)\/$", "https://extremismterms.adl.org\1") -> https://extremismterms.adl.org/glossary/inverted-red-triangle | F10: {=_xlfn.LET(_xlpm.rowNum,MATCH(E10,'glossaryterms-export'!C:C,0), IF(AND(NOT(ISBLANK(INDEX('glossaryterms-export'!H:H,_xlpm.rowNum))),ISBLANK(INDEX('glossaryterms-export'!I:I,_xlpm.rowNum))),"Ready to Fix",""))} | G10: 10513 | H10: 9359 | I10: 1.1233038 | J10: 26.462763 | K10: 56127
A11: 10 | B11: https://www.adl.org/resources/backgrounder/qanon | C11: /glossary/ncswic-nothing-can-stop-what-coming/ | D11: Y | E11: =_xlfn.REGEXREPLACE(C11, "(.*)\/$", "https://extremismterms.adl.org\1") -> https://extremismterms.adl.org/glossary/ncswic-nothing-can-stop-what-coming | F11: {=_xlfn.LET(_xlpm.rowNum,MATCH(E11,'glossaryterms-export'!C:C,0), IF(AND(NOT(ISBLANK(INDEX('glossaryterms-export'!H:H,_xlpm.rowNum))),ISBLANK(INDEX('glossaryterms-export'!I:I,_xlpm.rowNum))),"Ready to Fix",""))} | G11: 10426 | H11: 9154 | I11: 1.1389556 | J11: 17.279659 | K11: 41458
A12: 11 | B12: https://www.adl.org/resources/article/another-weekend-hate-neo-nazis-gather-florida | C12: /glossary/order-black-sun/ | E12: =_xlfn.REGEXREPLACE(C12, "(.*)\/$", "https://extremismterms.adl.org\1") -> https://extremismterms.adl.org/glossary/order-black-sun | F12: {=_xlfn.LET(_xlpm.rowNum,MATCH(E12,'glossaryterms-export'!C:C,0), IF(AND(NOT(ISBLANK(INDEX('glossaryterms-export'!H:H,_xlpm.rowNum))),ISBLANK(INDEX('glossaryterms-export'!I:I,_xlpm.rowNum))),"Ready to Fix",""))} -> Ready to Fix | G12: 8512 | H12: 7552 | I12: 1.1271186 | J12: 17.350106 | K12: 33054
A13: 12 | C13: /glossary/dumbs/ | E13: =_xlfn.REGEXREPLACE(C13, "(.*)\/$", "https://extremismterms.adl.org\1") -> https://extremismterms.adl.org/glossary/dumbs | F13: {=_xlfn.LET(_xlpm.rowNum,MATCH(E13,'glossaryterms-export'!C:C,0), IF(AND(NOT(ISBLANK(INDEX('glossaryterms-export'!H:H,_xlpm.rowNum))),ISBLANK(INDEX('glossaryterms-export'!I:I,_xlpm.rowNum))),"Ready to Fix",""))} | G13: 8429 | H13: 7382 | I13: 1.1418315 | J13: 24.283392 | K13: 34894
A14: 13 | B14: https://www.adl.org/resources/backgrounder/proud-boys | C14: /glossary/fuck-around-and-find-out-fafo/ | D14: Y | E14: =_xlfn.REGEXREPLACE(C14, "(.*)\/$", "https://extremismterms.adl.org\1") -> https://extremismterms.adl.org/glossary/fuck-around-and-find-out-fafo | F14: {=_xlfn.LET(_xlpm.rowNum,MATCH(E14,'glossaryterms-export'!C:C,0), IF(AND(NOT(ISBLANK(INDEX('glossaryterms-export'!H:H,_xlpm.rowNum))),ISBLANK(INDEX('glossaryterms-export'!I:I,_xlpm.rowNum))),"Ready to Fix",""))} | G14: 8128 | H14: 7141 | I14: 1.1382159 | J14: 23.247724 | K14: 32699
A15: 14 | B15: https://www.adl.org/resources/article/coded-hate-extremists-weaponize-seemingly-innocuous-content-promote-bigotry | C15: /glossary/noticing/ | D15: Y | E15: =_xlfn.REGEXREPLACE(C15, "(.*)\/$", "https://extremismterms.adl.org\1") -> https://extremismterms.adl.org/glossary/noticing | F15: {=_xlfn.LET(_xlpm.rowNum,MATCH(E15,'glossaryterms-export'!C:C,0), IF(AND(NOT(ISBLANK(INDEX('glossaryterms-export'!H:H,_xlpm.rowNum))),ISBLANK(INDEX('glossaryterms-export'!I:I,_xlpm.rowNum))),"Ready to Fix",""))} | G15: 7020 | H15: 5850 | I15: 1.2 | J15: 22.350256 | K15: 19678
A16: 15 | B16: https://www.adl.org/resources/backgrounder/sovereign-citizen-movement-united-states | C16: /glossary/david-straight/ | D16: Y | E16: =_xlfn.REGEXREPLACE(C16, "(.*)\/$", "https://extremismterms.adl.org\1") -> https://extremismterms.adl.org/glossary/david-straight | F16: {=_xlfn.LET(_xlpm.rowNum,MATCH(E16,'glossaryterms-export'!C:C,0), IF(AND(NOT(ISBLANK(INDEX('glossaryterms-export'!H:H,_xlpm.rowNum))),ISBLANK(INDEX('glossaryterms-export'!I:I,_xlpm.rowNum))),"Ready to Fix",""))} | G16: 6215 | H16: 5235 | I16: 1.1872015 | J16: 26.641261 | K16: 26040
A17: 16 | B17: https://www.adl.org/resources/article/coded-hate-extremists-weaponize-seemingly-innocuous-content-promote-bigotry | C17: /glossary/early-life-check/ | D17: Y | E17: =_xlfn.REGEXREPLACE(C17, "(.*)\/$", "https://extremismterms.adl.org\1") -> https://extremismterms.adl.org/glossary/early-life-check | F17: {=_xlfn.LET(_xlpm.rowNum,MATCH(E17,'glossaryterms-export'!C:C,0), IF(AND(NOT(ISBLANK(INDEX('glossaryterms-export'!H:H,_xlpm.rowNum))),ISBLANK(INDEX('glossaryterms-export'!I:I,_xlpm.rowNum))),"Ready to Fix",""))} -> Ready to Fix | G17: 6130 | H17: 5353 | I17: 1.1451523 | J17: 23.819727 | K17: 20403
A18: 17 | C18: /glossary/patriotswin/ | E18: =_xlfn.REGEXREPLACE(C18, "(.*)\/$", "https://extremismterms.adl.org\1") -> https://extremismterms.adl.org/glossary/patriotswin | F18: {=_xlfn.LET(_xlpm.rowNum,MATCH(E18,'glossaryterms-export'!C:C,0), IF(AND(NOT(ISBLANK(INDEX('glossaryterms-export'!H:H,_xlpm.rowNum))),ISBLANK(INDEX('glossaryterms-export'!I:I,_xlpm.rowNum))),"Ready to Fix",""))} | G18: 5954 | H18: 5011 | I18: 1.188186 | J18: 11.144482 | K18: 22856
A19: 18 | B19: https://www.adl.org/resources/article/coded-hate-extremists-weaponize-seemingly-innocuous-content-promote-bigotry | C19: /glossary/never-lose-your-smile/ | D19: Y | E19: =_xlfn.REGEXREPLACE(C19, "(.*)\/$", "https://extremismterms.adl.org\1") -> https://extremismterms.adl.org/glossary/never-lose-your-smile | F19: {=_xlfn.LET(_xlpm.rowNum,MATCH(E19,'glossaryterms-export'!C:C,0), IF(AND(NOT(ISBLANK(INDEX('glossaryterms-export'!H:H,_xlpm.rowNum))),ISBLANK(INDEX('glossaryterms-export'!I:I,_xlpm.rowNum))),"Ready to Fix",""))} | G19: 5932 | H19: 5191 | I19: 1.1427471 | J19: 22.255635 | K19: 18192
A20: 19 | B20: https://www.adl.org/resources/backgrounder/sovereign-citizen-movement-united-states | C20: /glossary/american-state-national/ | D20: Y | E20: =_xlfn.REGEXREPLACE(C20, "(.*)\/$", "https://extremismterms.adl.org\1") -> https://extremismterms.adl.org/glossary/american-state-national | F20: {=_xlfn.LET(_xlpm.rowNum,MATCH(E20,'glossaryterms-export'!C:C,0), IF(AND(NOT(ISBLANK(INDEX('glossaryterms-export'!H:H,_xlpm.rowNum))),ISBLANK(INDEX('glossaryterms-export'!I:I,_xlpm.rowNum))),"Ready to Fix",""))} | G20: 5885 | H20: 5092 | I20: 1.1557345 | J20: 28.530047 | K20: 24202
A21: 20 | C21: /glossary/brother-nathanael/ | E21: =_xlfn.REGEXREPLACE(C21, "(.*)\/$", "https://extremismterms.adl.org\1") -> https://extremismterms.adl.org/glossary/brother-nathanael | F21: {=_xlfn.LET(_xlpm.rowNum,MATCH(E21,'glossaryterms-export'!C:C,0), IF(AND(NOT(ISBLANK(INDEX('glossaryterms-export'!H:H,_xlpm.rowNum))),ISBLANK(INDEX('glossaryterms-export'!I:I,_xlpm.rowNum))),"Ready to Fix",""))} -> Ready to Fix | G21: 5831 | H21: 5110 | I21: 1.1410959 | J21: 29.717417 | K21: 30312
A22: 21 | C22: /glossary/betar-usa/ | E22: =_xlfn.REGEXREPLACE(C22, "(.*)\/$", "https://extremismterms.adl.org\1") -> https://extremismterms.adl.org/glossary/betar-usa | F22: {=_xlfn.LET(_xlpm.rowNum,MATCH(E22,'glossaryterms-export'!C:C,0), IF(AND(NOT(ISBLANK(INDEX('glossaryterms-export'!H:H,_xlpm.rowNum))),ISBLANK(INDEX('glossaryterms-export'!I:I,_xlpm.rowNum))),"Ready to Fix",""))} | G22: 5783 | H22: 4526 | I22: 1.2777287 | J22: 39.036456 | K22: 22396
A23: 22 | B23: https://www.adl.org/resources/article/terrorgram-collective-international-terrorists-promoting-violence-and-white | C23: /glossary/terrorgram/ | E23: =_xlfn.REGEXREPLACE(C23, "(.*)\/$", "https://extremismterms.adl.org\1") -> https://extremismterms.adl.org/glossary/terrorgram | F23: {=_xlfn.LET(_xlpm.rowNum,MATCH(E23,'glossaryterms-export'!C:C,0), IF(AND(NOT(ISBLANK(INDEX('glossaryterms-export'!H:H,_xlpm.rowNum))),ISBLANK(INDEX('glossaryterms-export'!I:I,_xlpm.rowNum))),"Ready to Fix",""))} -> Ready to Fix | G23: 5670 | H23: 4906 | I23: 1.1557277 | J23: 26.67713 | K23: 25551
A24: 23 | C24: /glossary/matt-forney/ | E24: =_xlfn.REGEXREPLACE(C24, "(.*)\/$", "https://extremismterms.adl.org\1") -> https://extremismterms.adl.org/glossary/matt-forney | F24: {=_xlfn.LET(_xlpm.rowNum,MATCH(E24,'glossaryterms-export'!C:C,0), IF(AND(NOT(ISBLANK(INDEX('glossaryterms-export'!H:H,_xlpm.rowNum))),ISBLANK(INDEX('glossaryterms-export'!I:I,_xlpm.rowNum))),"Ready to Fix",""))} -> Ready to Fix | G24: 5522 | H24: 4995 | I24: 1.1055055 | J24: 10.004404 | K24: 22388
A25: 24 | C25: /glossary/died-suddenly/ | E25: =_xlfn.REGEXREPLACE(C25, "(.*)\/$", "https://extremismterms.adl.org\1") -> https://extremismterms.adl.org/glossary/died-suddenly | F25: {=_xlfn.LET(_xlpm.rowNum,MATCH(E25,'glossaryterms-export'!C:C,0), IF(AND(NOT(ISBLANK(INDEX('glossaryterms-export'!H:H,_xlpm.rowNum))),ISBLANK(INDEX('glossaryterms-export'!I:I,_xlpm.rowNum))),"Ready to Fix",""))} | G25: 5182 | H25: 4489 | I25: 1.1543774 | J25: 20.714413 | K25: 20463
A26: 25 | C26: /glossary/turning-point-usa-tpusa/ | E26: =_xlfn.REGEXREPLACE(C26, "(.*)\/$", "https://extremismterms.adl.org\1") -> https://extremismterms.adl.org/glossary/turning-point-usa-tpusa | F26: {=_xlfn.LET(_xlpm.rowNum,MATCH(E26,'glossaryterms-export'!C:C,0), IF(AND(NOT(ISBLANK(INDEX('glossaryterms-export'!H:H,_xlpm.rowNum))),ISBLANK(INDEX('glossaryterms-export'!I:I,_xlpm.rowNum))),"Ready to Fix",""))} | G26: 4985 | H26: 4199 | I26: 1.1871874 | J26: 29.699214 | K26: 14359
A27: 26 | C27: /resources/article/qanon-glossary/ | E27: =_xlfn.REGEXREPLACE(C27, "(.*)\/$", "https://extremismterms.adl.org\1") -> https://extremismterms.adl.org/resources/article/qanon-glossary | F27: {=_xlfn.LET(_xlpm.rowNum,MATCH(E27,'glossaryterms-export'!C:C,0), IF(AND(NOT(ISBLANK(INDEX('glossaryterms-export'!H:H,_xlpm.rowNum))),ISBLANK(INDEX('glossaryterms-export'!I:I,_xlpm.rowNum))),"Ready to Fix",""))} | G27: 4733 | H27: 3857 | I27: 1.2271195 | J27: 85.933109 | K27: 34045
A28: 27 | B28: https://www.adl.org/resources/article/coded-hate-extremists-weaponize-seemingly-innocuous-content-promote-bigotry | C28: /glossary/271k/ | D28: Y | E28: =_xlfn.REGEXREPLACE(C28, "(.*)\/$", "https://extremismterms.adl.org\1") -> https://extremismterms.adl.org/glossary/271k | F28: {=_xlfn.LET(_xlpm.rowNum,MATCH(E28,'glossaryterms-export'!C:C,0), IF(AND(NOT(ISBLANK(INDEX('glossaryterms-export'!H:H,_xlpm.rowNum))),ISBLANK(INDEX('glossaryterms-export'!I:I,_xlpm.rowNum))),"Ready to Fix",""))} | G28: 4667 | H28: 4132 | I28: 1.1294773 | J28: 19.77759 | K28: 16311
A29: 28 | B29: https://www.adl.org/resources/backgrounder/christian-identity-movement | C29: /glossary/christian-identity/ | D29: Y | E29: =_xlfn.REGEXREPLACE(C29, "(.*)\/$", "https://extremismterms.adl.org\1") -> https://extremismterms.adl.org/glossary/christian-identity | F29: {=_xlfn.LET(_xlpm.rowNum,MATCH(E29,'glossaryterms-export'!C:C,0), IF(AND(NOT(ISBLANK(INDEX('glossaryterms-export'!H:H,_xlpm.rowNum))),ISBLANK(INDEX('glossaryterms-export'!I:I,_xlpm.rowNum))),"Ready to Fix",""))} | G29: 4627 | H29: 3871 | I29: 1.1952984 | J29: 36.0589 | K29: 12138
A30: 29 | C30: /glossary/false-flag/ | E30: =_xlfn.REGEXREPLACE(C30, "(.*)\/$", "https://extremismterms.adl.org\1") -> https://extremismterms.adl.org/glossary/false-flag | F30: {=_xlfn.LET(_xlpm.rowNum,MATCH(E30,'glossaryterms-export'!C:C,0), IF(AND(NOT(ISBLANK(INDEX('glossaryterms-export'!H:H,_xlpm.rowNum))),ISBLANK(INDEX('glossaryterms-export'!I:I,_xlpm.rowNum))),"Ready to Fix",""))} | G30: 4569 | H30: 3924 | I30: 1.1643731 | J30: 21.557594 | K30: 17061
A31: 30 | B31: https://www.adl.org/resources/backgrounder/blood-tribe | C31: /glossary/christopher-pohlhaus/ | D31: Y | E31: =_xlfn.REGEXREPLACE(C31, "(.*)\/$", "https://extremismterms.adl.org\1") -> https://extremismterms.adl.org/glossary/christopher-pohlhaus | F31: {=_xlfn.LET(_xlpm.rowNum,MATCH(E31,'glossaryterms-export'!C:C,0), IF(AND(NOT(ISBLANK(INDEX('glossaryterms-export'!H:H,_xlpm.rowNum))),ISBLANK(INDEX('glossaryterms-export'!I:I,_xlpm.rowNum))),"Ready to Fix",""))} -> Ready to Fix | G31: 4486 | H31: 3964 | I31: 1.1316852 | J31: 27.282291 | K31: 23341
A32: 31 | C32: /glossary/thomas-dalton/ | E32: =_xlfn.REGEXREPLACE(C32, "(.*)\/$", "https://extremismterms.adl.org\1") -> https://extremismterms.adl.org/glossary/thomas-dalton | F32: {=_xlfn.LET(_xlpm.rowNum,MATCH(E32,'glossaryterms-export'!C:C,0), IF(AND(NOT(ISBLANK(INDEX('glossaryterms-export'!H:H,_xlpm.rowNum))),ISBLANK(INDEX('glossaryterms-export'!I:I,_xlpm.rowNum))),"Ready to Fix",""))} | G32: 4362 | H32: 3646 | I32: 1.1963796 | J32: 44.75864 | K32: 25312
A33: 32 | C33: /glossary/whiteblack-hats/ | E33: =_xlfn.REGEXREPLACE(C33, "(.*)\/$", "https://extremismterms.adl.org\1") -> https://extremismterms.adl.org/glossary/whiteblack-hats | F33: {=_xlfn.LET(_xlpm.rowNum,MATCH(E33,'glossaryterms-export'!C:C,0), IF(AND(NOT(ISBLANK(INDEX('glossaryterms-export'!H:H,_xlpm.rowNum))),ISBLANK(INDEX('glossaryterms-export'!I:I,_xlpm.rowNum))),"Ready to Fix",""))} | G33: 4226 | H33: 3607 | I33: 1.1716108 | J33: 24.054893 | K33: 17304
A34: 33 | B34: https://www.adl.org/resources/article/coded-hate-extremists-weaponize-seemingly-innocuous-content-promote-bigotry | C34: /glossary/six-million-cookies/ | D34: Y | E34: =_xlfn.REGEXREPLACE(C34, "(.*)\/$", "https://extremismterms.adl.org\1") -> https://extremismterms.adl.org/glossary/six-million-cookies | F34: {=_xlfn.LET(_xlpm.rowNum,MATCH(E34,'glossaryterms-export'!C:C,0), IF(AND(NOT(ISBLANK(INDEX('glossaryterms-export'!H:H,_xlpm.rowNum))),ISBLANK(INDEX('glossaryterms-export'!I:I,_xlpm.rowNum))),"Ready to Fix",""))} | G34: 4085 | H34: 3592 | I34: 1.1372494 | J34: 16.657294 | K34: 14740
A35: 34 | C35: /glossary/traditionalist-catholicism/ | E35: =_xlfn.REGEXREPLACE(C35, "(.*)\/$", "https://extremismterms.adl.org\1") -> https://extremismterms.adl.org/glossary/traditionalist-catholicism | F35: {=_xlfn.LET(_xlpm.rowNum,MATCH(E35,'glossaryterms-export'!C:C,0), IF(AND(NOT(ISBLANK(INDEX('glossaryterms-export'!H:H,_xlpm.rowNum))),ISBLANK(INDEX('glossaryterms-export'!I:I,_xlpm.rowNum))),"Ready to Fix",""))} | G35: 3748 | H35: 3152 | I35: 1.1890863 | J35: 51.120241 | K35: 20868
A36: 35 | C36: /glossary/chemtrails/ | E36: =_xlfn.REGEXREPLACE(C36, "(.*)\/$", "https://extremismterms.adl.org\1") -> https://extremismterms.adl.org/glossary/chemtrails | F36: {=_xlfn.LET(_xlpm.rowNum,MATCH(E36,'glossaryterms-export'!C:C,0), IF(AND(NOT(ISBLANK(INDEX('glossaryterms-export'!H:H,_xlpm.rowNum))),ISBLANK(INDEX('glossaryterms-export'!I:I,_xlpm.rowNum))),"Ready to Fix",""))} | G36: 3703 | H36: 3309 | I36: 1.1190692 | J36: 24.314294 | K36: 15074
A37: 36 | B37: https://www.adl.org/resources/backgrounder/great-replacement-explainer | C37: /glossary/great-replacement-replacement-theory/ | D37: Y | E37: =_xlfn.REGEXREPLACE(C37, "(.*)\/$", "https://extremismterms.adl.org\1") -> https://extremismterms.adl.org/glossary/great-replacement-replacement-theory | F37: {=_xlfn.LET(_xlpm.rowNum,MATCH(E37,'glossaryterms-export'!C:C,0), IF(AND(NOT(ISBLANK(INDEX('glossaryterms-export'!H:H,_xlpm.rowNum))),ISBLANK(INDEX('glossaryterms-export'!I:I,_xlpm.rowNum))),"Ready to Fix",""))} -> Ready to Fix | G37: 3694 | H37: 3376 | I37: 1.0941943 | J37: 25.452903 | K37: 15087
A38: 37 | B38: https://www.adl.org/resources/backgrounder/qanon | C38: /glossary/wwg1wga/ | D38: Y | E38: =_xlfn.REGEXREPLACE(C38, "(.*)\/$", "https://extremismterms.adl.org\1") -> https://extremismterms.adl.org/glossary/wwg1wga | F38: {=_xlfn.LET(_xlpm.rowNum,MATCH(E38,'glossaryterms-export'!C:C,0), IF(AND(NOT(ISBLANK(INDEX('glossaryterms-export'!H:H,_xlpm.rowNum))),ISBLANK(INDEX('glossaryterms-export'!I:I,_xlpm.rowNum))),"Ready to Fix",""))} | G38: 3625 | H38: 3192 | I38: 1.1356516 | J38: 19.915727 | K38: 14228
A39: 38 | C39: /glossary/murder-seth-rich/ | E39: =_xlfn.REGEXREPLACE(C39, "(.*)\/$", "https://extremismterms.adl.org\1") -> https://extremismterms.adl.org/glossary/murder-seth-rich | F39: {=_xlfn.LET(_xlpm.rowNum,MATCH(E39,'glossaryterms-export'!C:C,0), IF(AND(NOT(ISBLANK(INDEX('glossaryterms-export'!H:H,_xlpm.rowNum))),ISBLANK(INDEX('glossaryterms-export'!I:I,_xlpm.rowNum))),"Ready to Fix",""))} | G39: 3162 | H39: 2848 | I39: 1.1102528 | J39: 20.57198 | K39: 12531
A40: 39 | C40: /glossary/ryan-j-murdough/ | E40: =_xlfn.REGEXREPLACE(C40, "(.*)\/$", "https://extremismterms.adl.org\1") -> https://extremismterms.adl.org/glossary/ryan-j-murdough | F40: {=_xlfn.LET(_xlpm.rowNum,MATCH(E40,'glossaryterms-export'!C:C,0), IF(AND(NOT(ISBLANK(INDEX('glossaryterms-export'!H:H,_xlpm.rowNum))),ISBLANK(INDEX('glossaryterms-export'!I:I,_xlpm.rowNum))),"Ready to Fix",""))} -> Ready to Fix | G40: 3160 | H40: 2599 | I40: 1.2158523 | J40: 21.276645 | K40: 11128
A41: 40 | C41: /glossary/cultural-marxism/ | E41: =_xlfn.REGEXREPLACE(C41, "(.*)\/$", "https://extremismterms.adl.org\1") -> https://extremismterms.adl.org/glossary/cultural-marxism | F41: {=_xlfn.LET(_xlpm.rowNum,MATCH(E41,'glossaryterms-export'!C:C,0), IF(AND(NOT(ISBLANK(INDEX('glossaryterms-export'!H:H,_xlpm.rowNum))),ISBLANK(INDEX('glossaryterms-export'!I:I,_xlpm.rowNum))),"Ready to Fix",""))} | G41: 2990 | H41: 2629 | I41: 1.1373146 | J41: 31.999239 | K41: 8341
A42: 41 | B42: https://www.adl.org/resources/backgrounder/american-blackshirts-movement-abm | C42: /glossary/american-blackshirts/ | D42: Y | E42: =_xlfn.REGEXREPLACE(C42, "(.*)\/$", "https://extremismterms.adl.org\1") -> https://extremismterms.adl.org/glossary/american-blackshirts | F42: {=_xlfn.LET(_xlpm.rowNum,MATCH(E42,'glossaryterms-export'!C:C,0), IF(AND(NOT(ISBLANK(INDEX('glossaryterms-export'!H:H,_xlpm.rowNum))),ISBLANK(INDEX('glossaryterms-export'!I:I,_xlpm.rowNum))),"Ready to Fix",""))} -> Ready to Fix | G42: 2911 | H42: 2532 | I42: 1.149684 | J42: 19.254739 | K42: 10656
A43: 42 | B43: https://www.adl.org/resources/backgrounder/qanon | C43: /glossary/great-awakening-map/ | D43: Y | E43: =_xlfn.REGEXREPLACE(C43, "(.*)\/$", "https://extremismterms.adl.org\1") -> https://extremismterms.adl.org/glossary/great-awakening-map | F43: {=_xlfn.LET(_xlpm.rowNum,MATCH(E43,'glossaryterms-export'!C:C,0), IF(AND(NOT(ISBLANK(INDEX('glossaryterms-export'!H:H,_xlpm.rowNum))),ISBLANK(INDEX('glossaryterms-export'!I:I,_xlpm.rowNum))),"Ready to Fix",""))} | G43: 2909 | H43: 2508 | I43: 1.1598884 | J43: 15.051834 | K43: 12066
A44: 43 | B44: https://www.adl.org/resources/backgrounder/qanon | C44: /glossary/19th-president/ | D44: Y | E44: =_xlfn.REGEXREPLACE(C44, "(.*)\/$", "https://extremismterms.adl.org\1") -> https://extremismterms.adl.org/glossary/19th-president | F44: {=_xlfn.LET(_xlpm.rowNum,MATCH(E44,'glossaryterms-export'!C:C,0), IF(AND(NOT(ISBLANK(INDEX('glossaryterms-export'!H:H,_xlpm.rowNum))),ISBLANK(INDEX('glossaryterms-export'!I:I,_xlpm.rowNum))),"Ready to Fix",""))} | G44: 2869 | H44: 2562 | I44: 1.1198283 | J44: 35.900468 | K44: 10045
A45: 44 | B45: https://www.adl.org/resources/backgrounder/goyim-defense-league | C45: /glossary/goyim-defense-league/ | D45: Y | E45: =_xlfn.REGEXREPLACE(C45, "(.*)\/$", "https://extremismterms.adl.org\1") -> https://extremismterms.adl.org/glossary/goyim-defense-league | F45: {=_xlfn.LET(_xlpm.rowNum,MATCH(E45,'glossaryterms-export'!C:C,0), IF(AND(NOT(ISBLANK(INDEX('glossaryterms-export'!H:H,_xlpm.rowNum))),ISBLANK(INDEX('glossaryterms-export'!I:I,_xlpm.rowNum))),"Ready to Fix",""))} | G45: 2650 | H45: 2429 | I45: 1.0909839 | J45: 18.164265 | K45: 6506
A46: 45 | B46: https://www.adl.org/resources/article/coded-hate-extremists-weaponize-seemingly-innocuous-content-promote-bigotry | C46: /glossary/my-heart-goes-out-you/ | D46: Y | E46: =_xlfn.REGEXREPLACE(C46, "(.*)\/$", "https://extremismterms.adl.org\1") -> https://extremismterms.adl.org/glossary/my-heart-goes-out-you | F46: {=_xlfn.LET(_xlpm.rowNum,MATCH(E46,'glossaryterms-export'!C:C,0), IF(AND(NOT(ISBLANK(INDEX('glossaryterms-export'!H:H,_xlpm.rowNum))),ISBLANK(INDEX('glossaryterms-export'!I:I,_xlpm.rowNum))),"Ready to Fix",""))} | G46: 2563 | H46: 2343 | I46: 1.0938967 | J46: 17.987623 | K46: 6138
A47: 46 | B47: https://www.adl.org/resources/article/white-supremacist-propaganda-focused-jews-and-immigrants-2024 | C47: /glossary/new-england-white-network/ | D47: Y | E47: =_xlfn.REGEXREPLACE(C47, "(.*)\/$", "https://extremismterms.adl.org\1") -> https://extremismterms.adl.org/glossary/new-england-white-network | F47: {=_xlfn.LET(_xlpm.rowNum,MATCH(E47,'glossaryterms-export'!C:C,0), IF(AND(NOT(ISBLANK(INDEX('glossaryterms-export'!H:H,_xlpm.rowNum))),ISBLANK(INDEX('glossaryterms-export'!I:I,_xlpm.rowNum))),"Ready to Fix",""))} -> Ready to Fix | G47: 2563 | H47: 2235 | I47: 1.1467562 | J47: 22.367338 | K47: 9495
A48: 47 | C48: /glossary/parents-rights-movement/ | E48: =_xlfn.REGEXREPLACE(C48, "(.*)\/$", "https://extremismterms.adl.org\1") -> https://extremismterms.adl.org/glossary/parents-rights-movement | F48: {=_xlfn.LET(_xlpm.rowNum,MATCH(E48,'glossaryterms-export'!C:C,0), IF(AND(NOT(ISBLANK(INDEX('glossaryterms-export'!H:H,_xlpm.rowNum))),ISBLANK(INDEX('glossaryterms-export'!I:I,_xlpm.rowNum))),"Ready to Fix",""))} | G48: 2553 | H48: 2312 | I48: 1.1042388 | J48: 26.731834 | K48: 7701
A49: 48 | C49: /glossary/stew-peters/ | E49: =_xlfn.REGEXREPLACE(C49, "(.*)\/$", "https://extremismterms.adl.org\1") -> https://extremismterms.adl.org/glossary/stew-peters | F49: {=_xlfn.LET(_xlpm.rowNum,MATCH(E49,'glossaryterms-export'!C:C,0), IF(AND(NOT(ISBLANK(INDEX('glossaryterms-export'!H:H,_xlpm.rowNum))),ISBLANK(INDEX('glossaryterms-export'!I:I,_xlpm.rowNum))),"Ready to Fix",""))} -> Ready to Fix | G49: 2520 | H49: 2255 | I49: 1.1175166 | J49: 21.247894 | K49: 7742
A50: 49 | B50: https://www.adl.org/resources/article/coded-hate-extremists-weaponize-seemingly-innocuous-content-promote-bigotry | C50: /glossary/fatigue-black-fatigue-jew-fatigue/ | D50: Y | E50: =_xlfn.REGEXREPLACE(C50, "(.*)\/$", "https://extremismterms.adl.org\1") -> https://extremismterms.adl.org/glossary/fatigue-black-fatigue-jew-fatigue | F50: {=_xlfn.LET(_xlpm.rowNum,MATCH(E50,'glossaryterms-export'!C:C,0), IF(AND(NOT(ISBLANK(INDEX('glossaryterms-export'!H:H,_xlpm.rowNum))),ISBLANK(INDEX('glossaryterms-export'!I:I,_xlpm.rowNum))),"Ready to Fix",""))} | G50: 2438 | H50: 2194 | I50: 1.1112124 | J50: 24.949407 | K50: 6300
A51: 50 | B51: https://www.adl.org/resources/backgrounder/qanon | C51: /glossary/q-clock/ | D51: Y | E51: =_xlfn.REGEXREPLACE(C51, "(.*)\/$", "https://extremismterms.adl.org\1") -> https://extremismterms.adl.org/glossary/q-clock | F51: {=_xlfn.LET(_xlpm.rowNum,MATCH(E51,'glossaryterms-export'!C:C,0), IF(AND(NOT(ISBLANK(INDEX('glossaryterms-export'!H:H,_xlpm.rowNum))),ISBLANK(INDEX('glossaryterms-export'!I:I,_xlpm.rowNum))),"Ready to Fix",""))} | G51: 2311 | H51: 2012 | I51: 1.1486083 | J51: 20.536282 | K51: 9376
A52: 51 | C52: /glossary/resistance-news-network-rnn/ | E52: =_xlfn.REGEXREPLACE(C52, "(.*)\/$", "https://extremismterms.adl.org\1") -> https://extremismterms.adl.org/glossary/resistance-news-network-rnn | F52: {=_xlfn.LET(_xlpm.rowNum,MATCH(E52,'glossaryterms-export'!C:C,0), IF(AND(NOT(ISBLANK(INDEX('glossaryterms-export'!H:H,_xlpm.rowNum))),ISBLANK(INDEX('glossaryterms-export'!I:I,_xlpm.rowNum))),"Ready to Fix",""))} | G52: 2307 | H52: 1965 | I52: 1.1740458 | J52: 34.975064 | K52: 11539
A53: 52 | B53: https://www.adl.org/resources/report/antisemitic-conspiracies-about-911-endure-20-years-later | C53: /glossary/dancing-israelis/ | D53: Y | E53: =_xlfn.REGEXREPLACE(C53, "(.*)\/$", "https://extremismterms.adl.org\1") -> https://extremismterms.adl.org/glossary/dancing-israelis | F53: {=_xlfn.LET(_xlpm.rowNum,MATCH(E53,'glossaryterms-export'!C:C,0), IF(AND(NOT(ISBLANK(INDEX('glossaryterms-export'!H:H,_xlpm.rowNum))),ISBLANK(INDEX('glossaryterms-export'!I:I,_xlpm.rowNum))),"Ready to Fix",""))} -> Ready to Fix | G53: 2244 | H53: 2047 | I53: 1.0962384 | J53: 10.30679 | K53: 7018
A54: 53 | B54: https://www.adl.org/resources/article/coded-hate-extremists-weaponize-seemingly-innocuous-content-promote-bigotry | C54: /glossary/juice/ | D54: Y | E54: =_xlfn.REGEXREPLACE(C54, "(.*)\/$", "https://extremismterms.adl.org\1") -> https://extremismterms.adl.org/glossary/juice | F54: {=_xlfn.LET(_xlpm.rowNum,MATCH(E54,'glossaryterms-export'!C:C,0), IF(AND(NOT(ISBLANK(INDEX('glossaryterms-export'!H:H,_xlpm.rowNum))),ISBLANK(INDEX('glossaryterms-export'!I:I,_xlpm.rowNum))),"Ready to Fix",""))} | G54: 2176 | H54: 1936 | I54: 1.1239669 | J54: 12.556818 | K54: 5641
A55: 54 | B55: https://www.adl.org/resources/profile/nation-islam | C55: /glossary/yakub/ | E55: =_xlfn.REGEXREPLACE(C55, "(.*)\/$", "https://extremismterms.adl.org\1") -> https://extremismterms.adl.org/glossary/yakub | F55: {=_xlfn.LET(_xlpm.rowNum,MATCH(E55,'glossaryterms-export'!C:C,0), IF(AND(NOT(ISBLANK(INDEX('glossaryterms-export'!H:H,_xlpm.rowNum))),ISBLANK(INDEX('glossaryterms-export'!I:I,_xlpm.rowNum))),"Ready to Fix",""))} | G55: 2101 | H55: 1807 | I55: 1.1627006 | J55: 28.810736 | K55: 8126
A56: 55 | C56: /resources/glossary-term/2021-israel-hamas-conflict-0/ | F56: {=_xlfn.LET(_xlpm.rowNum,MATCH(E56,'glossaryterms-export'!C:C,0), IF(AND(NOT(ISBLANK(INDEX('glossaryterms-export'!H:H,_xlpm.rowNum))),ISBLANK(INDEX('glossaryterms-export'!I:I,_xlpm.rowNum))),"Ready to Fix",""))} | G56: 2095 | H56: 1519 | I56: 1.3791968 | J56: 79.652403 | K56: 14489
A57: 56 | C57: /glossary/ten-days-darkness/ | E57: =_xlfn.REGEXREPLACE(C57, "(.*)\/$", "https://extremismterms.adl.org\1") -> https://extremismterms.adl.org/glossary/ten-days-darkness | F57: {=_xlfn.LET(_xlpm.rowNum,MATCH(E57,'glossaryterms-export'!C:C,0), IF(AND(NOT(ISBLANK(INDEX('glossaryterms-export'!H:H,_xlpm.rowNum))),ISBLANK(INDEX('glossaryterms-export'!I:I,_xlpm.rowNum))),"Ready to Fix",""))} | G57: 2025 | H57: 1782 | I57: 1.1363636 | J57: 28.407407 | K57: 8122
A58: 57 | B58: https://www.adl.org/resources/backgrounder/764 | C58: /glossary/order-nine-angles-o9a-ona/ | D58: Y | E58: =_xlfn.REGEXREPLACE(C58, "(.*)\/$", "https://extremismterms.adl.org\1") -> https://extremismterms.adl.org/glossary/order-nine-angles-o9a-ona | F58: {=_xlfn.LET(_xlpm.rowNum,MATCH(E58,'glossaryterms-export'!C:C,0), IF(AND(NOT(ISBLANK(INDEX('glossaryterms-export'!H:H,_xlpm.rowNum))),ISBLANK(INDEX('glossaryterms-export'!I:I,_xlpm.rowNum))),"Ready to Fix",""))} | G58: 2006 | H58: 1748 | I58: 1.1475973 | J58: 14.769451 | K58: 5223
A59: 58 | B59: https://www.adl.org/resources/backgrounder/accelerationism | C59: /glossary/injekt-division/ | D59: Y | E59: =_xlfn.REGEXREPLACE(C59, "(.*)\/$", "https://extremismterms.adl.org\1") -> https://extremismterms.adl.org/glossary/injekt-division | F59: {=_xlfn.LET(_xlpm.rowNum,MATCH(E59,'glossaryterms-export'!C:C,0), IF(AND(NOT(ISBLANK(INDEX('glossaryterms-export'!H:H,_xlpm.rowNum))),ISBLANK(INDEX('glossaryterms-export'!I:I,_xlpm.rowNum))),"Ready to Fix",""))} | G59: 2000 | H59: 1604 | I59: 1.2468828 | J59: 30.504988 | K59: 9803
A60: 59 | C60: /glossary/atlantic-nationalist-club-anc/ | E60: =_xlfn.REGEXREPLACE(C60, "(.*)\/$", "https://extremismterms.adl.org\1") -> https://extremismterms.adl.org/glossary/atlantic-nationalist-club-anc | F60: {=_xlfn.LET(_xlpm.rowNum,MATCH(E60,'glossaryterms-export'!C:C,0), IF(AND(NOT(ISBLANK(INDEX('glossaryterms-export'!H:H,_xlpm.rowNum))),ISBLANK(INDEX('glossaryterms-export'!I:I,_xlpm.rowNum))),"Ready to Fix",""))} -> Ready to Fix | G60: 1978 | H60: 1651 | I60: 1.1980618 | J60: 25.772259 | K60: 9091
A61: 60 | B61: https://www.adl.org/resources/backgrounder/qanon | C61: /glossary/q-0/ | D61: Y | E61: =_xlfn.REGEXREPLACE(C61, "(.*)\/$", "https://extremismterms.adl.org\1") -> https://extremismterms.adl.org/glossary/q-0 | F61: {=_xlfn.LET(_xlpm.rowNum,MATCH(E61,'glossaryterms-export'!C:C,0), IF(AND(NOT(ISBLANK(INDEX('glossaryterms-export'!H:H,_xlpm.rowNum))),ISBLANK(INDEX('glossaryterms-export'!I:I,_xlpm.rowNum))),"Ready to Fix",""))} | G61: 1920 | H61: 1713 | I61: 1.1208406 | J61: 16.838295 | K61: 7618
A62: 61 | B62: https://www.adl.org/resources/backgrounder/764 | C62: /glossary/764/ | D62: Y | E62: =_xlfn.REGEXREPLACE(C62, "(.*)\/$", "https://extremismterms.adl.org\1") -> https://extremismterms.adl.org/glossary/764 | F62: {=_xlfn.LET(_xlpm.rowNum,MATCH(E62,'glossaryterms-export'!C:C,0), IF(AND(NOT(ISBLANK(INDEX('glossaryterms-export'!H:H,_xlpm.rowNum))),ISBLANK(INDEX('glossaryterms-export'!I:I,_xlpm.rowNum))),"Ready to Fix",""))} | G62: 1874 | H62: 1677 | I62: 1.1174717 | J62: 30.322004 | K62: 8256
A63: 62 | B63: https://www.adl.org/holocaust-denial-anatomy-antisemitic-conspiracy-theory | C63: /glossary/david-irving/ | E63: =_xlfn.REGEXREPLACE(C63, "(.*)\/$", "https://extremismterms.adl.org\1") -> https://extremismterms.adl.org/glossary/david-irving | F63: {=_xlfn.LET(_xlpm.rowNum,MATCH(E63,'glossaryterms-export'!C:C,0), IF(AND(NOT(ISBLANK(INDEX('glossaryterms-export'!H:H,_xlpm.rowNum))),ISBLANK(INDEX('glossaryterms-export'!I:I,_xlpm.rowNum))),"Ready to Fix",""))} -> Ready to Fix | G63: 1854 | H63: 1502 | I63: 1.2343542 | J63: 65.053928 | K63: 9919
A64: 63 | C64: /glossary/open-borders-israel/ | E64: =_xlfn.REGEXREPLACE(C64, "(.*)\/$", "https://extremismterms.adl.org\1") -> https://extremismterms.adl.org/glossary/open-borders-israel | F64: {=_xlfn.LET(_xlpm.rowNum,MATCH(E64,'glossaryterms-export'!C:C,0), IF(AND(NOT(ISBLANK(INDEX('glossaryterms-export'!H:H,_xlpm.rowNum))),ISBLANK(INDEX('glossaryterms-export'!I:I,_xlpm.rowNum))),"Ready to Fix",""))} | G64: 1851 | H64: 1587 | I64: 1.1663516 | J64: 17.764335 | K64: 6873
A65: 64 | B65: https://www.adl.org/resources/backgrounder/accelerationism | C65: /glossary/national-socialist-resistance-front-nsrf/ | D65: Y | E65: =_xlfn.REGEXREPLACE(C65, "(.*)\/$", "https://extremismterms.adl.org\1") -> https://extremismterms.adl.org/glossary/national-socialist-resistance-front-nsrf | F65: {=_xlfn.LET(_xlpm.rowNum,MATCH(E65,'glossaryterms-export'!C:C,0), IF(AND(NOT(ISBLANK(INDEX('glossaryterms-export'!H:H,_xlpm.rowNum))),ISBLANK(INDEX('glossaryterms-export'!I:I,_xlpm.rowNum))),"Ready to Fix",""))} | G65: 1843 | H65: 1594 | I65: 1.1562108 | J65: 21.269762 | K65: 4580
A66: 65 | C66: /glossary/remigration/ | E66: =_xlfn.REGEXREPLACE(C66, "(.*)\/$", "https://extremismterms.adl.org\1") -> https://extremismterms.adl.org/glossary/remigration | F66: {=_xlfn.LET(_xlpm.rowNum,MATCH(E66,'glossaryterms-export'!C:C,0), IF(AND(NOT(ISBLANK(INDEX('glossaryterms-export'!H:H,_xlpm.rowNum))),ISBLANK(INDEX('glossaryterms-export'!I:I,_xlpm.rowNum))),"Ready to Fix",""))} | G66: 1839 | H66: 1621 | I66: 1.1344849 | J66: 21.797039 | K66: 6723
A67: 66 | B67: https://www.adl.org/resources/backgrounder/e-michael-jones | C67: /glossary/e-michael-jones/ | E67: =_xlfn.REGEXREPLACE(C67, "(.*)\/$", "https://extremismterms.adl.org\1") -> https://extremismterms.adl.org/glossary/e-michael-jones | F67: {=_xlfn.LET(_xlpm.rowNum,MATCH(E67,'glossaryterms-export'!C:C,0), IF(AND(NOT(ISBLANK(INDEX('glossaryterms-export'!H:H,_xlpm.rowNum))),ISBLANK(INDEX('glossaryterms-export'!I:I,_xlpm.rowNum))),"Ready to Fix",""))} -> Ready to Fix | G67: 1755 | H67: 1623 | I67: 1.0813309 | J67: 34.502157 | K67: 7559
A68: 67 | B68: https://www.adl.org/resources/article/coded-hate-extremists-weaponize-seemingly-innocuous-content-promote-bigotry | C68: /glossary/every-single-time/ | D68: Y | E68: =_xlfn.REGEXREPLACE(C68, "(.*)\/$", "https://extremismterms.adl.org\1") -> https://extremismterms.adl.org/glossary/every-single-time | F68: {=_xlfn.LET(_xlpm.rowNum,MATCH(E68,'glossaryterms-export'!C:C,0), IF(AND(NOT(ISBLANK(INDEX('glossaryterms-export'!H:H,_xlpm.rowNum))),ISBLANK(INDEX('glossaryterms-export'!I:I,_xlpm.rowNum))),"Ready to Fix",""))} | G68: 1734 | H68: 1547 | I68: 1.1208791 | J68: 15.892696 | K68: 4031
A69: 68 | B69: https://www.adl.org/resources/backgrounder/qanon | C69: /glossary/romana-didulo/ | D69: Y | E69: =_xlfn.REGEXREPLACE(C69, "(.*)\/$", "https://extremismterms.adl.org\1") -> https://extremismterms.adl.org/glossary/romana-didulo | F69: {=_xlfn.LET(_xlpm.rowNum,MATCH(E69,'glossaryterms-export'!C:C,0), IF(AND(NOT(ISBLANK(INDEX('glossaryterms-export'!H:H,_xlpm.rowNum))),ISBLANK(INDEX('glossaryterms-export'!I:I,_xlpm.rowNum))),"Ready to Fix",""))} | G69: 1709 | H69: 1577 | I69: 1.0837032 | J69: 28.029169 | K69: 6530
A70: 69 | C70: /glossary/follow-white-rabbit/ | E70: =_xlfn.REGEXREPLACE(C70, "(.*)\/$", "https://extremismterms.adl.org\1") -> https://extremismterms.adl.org/glossary/follow-white-rabbit | F70: {=_xlfn.LET(_xlpm.rowNum,MATCH(E70,'glossaryterms-export'!C:C,0), IF(AND(NOT(ISBLANK(INDEX('glossaryterms-export'!H:H,_xlpm.rowNum))),ISBLANK(INDEX('glossaryterms-export'!I:I,_xlpm.rowNum))),"Ready to Fix",""))} | G70: 1647 | H70: 1447 | I70: 1.138217 | J70: 13.949551 | K70: 6609
A71: 70 | C71: /glossary/khazars/ | E71: =_xlfn.REGEXREPLACE(C71, "(.*)\/$", "https://extremismterms.adl.org\1") -> https://extremismterms.adl.org/glossary/khazars | F71: {=_xlfn.LET(_xlpm.rowNum,MATCH(E71,'glossaryterms-export'!C:C,0), IF(AND(NOT(ISBLANK(INDEX('glossaryterms-export'!H:H,_xlpm.rowNum))),ISBLANK(INDEX('glossaryterms-export'!I:I,_xlpm.rowNum))),"Ready to Fix",""))} -> Ready to Fix | G71: 1644 | H71: 1475 | I71: 1.1145763 | J71: 29.472542 | K71: 5654
A72: 71 | C72: /glossary/psyop/ | E72: =_xlfn.REGEXREPLACE(C72, "(.*)\/$", "https://extremismterms.adl.org\1") -> https://extremismterms.adl.org/glossary/psyop | F72: {=_xlfn.LET(_xlpm.rowNum,MATCH(E72,'glossaryterms-export'!C:C,0), IF(AND(NOT(ISBLANK(INDEX('glossaryterms-export'!H:H,_xlpm.rowNum))),ISBLANK(INDEX('glossaryterms-export'!I:I,_xlpm.rowNum))),"Ready to Fix",""))} | G72: 1636 | H72: 1435 | I72: 1.1400697 | J72: 14.335889 | K72: 5959
A73: 72 | B73: https://www.adl.org/resources/backgrounder/accelerationism | C73: /glossary/american-futurist-0/ | D73: Y | E73: =_xlfn.REGEXREPLACE(C73, "(.*)\/$", "https://extremismterms.adl.org\1") -> https://extremismterms.adl.org/glossary/american-futurist-0 | F73: {=_xlfn.LET(_xlpm.rowNum,MATCH(E73,'glossaryterms-export'!C:C,0), IF(AND(NOT(ISBLANK(INDEX('glossaryterms-export'!H:H,_xlpm.rowNum))),ISBLANK(INDEX('glossaryterms-export'!I:I,_xlpm.rowNum))),"Ready to Fix",""))} | G73: 1568 | H73: 1363 | I73: 1.1504035 | J73: 22.763023 | K73: 4072
A74: 73 | C74: /glossary/scott-mckay/ | E74: =_xlfn.REGEXREPLACE(C74, "(.*)\/$", "https://extremismterms.adl.org\1") -> https://extremismterms.adl.org/glossary/scott-mckay | F74: {=_xlfn.LET(_xlpm.rowNum,MATCH(E74,'glossaryterms-export'!C:C,0), IF(AND(NOT(ISBLANK(INDEX('glossaryterms-export'!H:H,_xlpm.rowNum))),ISBLANK(INDEX('glossaryterms-export'!I:I,_xlpm.rowNum))),"Ready to Fix",""))} | G74: 1568 | H74: 1359 | I74: 1.1537896 | J74: 26.080942 | K74: 4784
A75: 74 | C75: /glossary/race-realism-racial-realism/ | E75: =_xlfn.REGEXREPLACE(C75, "(.*)\/$", "https://extremismterms.adl.org\1") -> https://extremismterms.adl.org/glossary/race-realism-racial-realism | F75: {=_xlfn.LET(_xlpm.rowNum,MATCH(E75,'glossaryterms-export'!C:C,0), IF(AND(NOT(ISBLANK(INDEX('glossaryterms-export'!H:H,_xlpm.rowNum))),ISBLANK(INDEX('glossaryterms-export'!I:I,_xlpm.rowNum))),"Ready to Fix",""))} | G75: 1529 | H75: 1372 | I75: 1.1144315 | J75: 20.147959 | K75: 6168
A76: 75 | C76: /glossary/ghost-face-gangster/ | E76: =_xlfn.REGEXREPLACE(C76, "(.*)\/$", "https://extremismterms.adl.org\1") -> https://extremismterms.adl.org/glossary/ghost-face-gangster | F76: {=_xlfn.LET(_xlpm.rowNum,MATCH(E76,'glossaryterms-export'!C:C,0), IF(AND(NOT(ISBLANK(INDEX('glossaryterms-export'!H:H,_xlpm.rowNum))),ISBLANK(INDEX('glossaryterms-export'!I:I,_xlpm.rowNum))),"Ready to Fix",""))} -> Ready to Fix | G76: 1528 | H76: 1307 | I76: 1.1690895 | J76: 30.078041 | K76: 5811
A77: 76 | B77: https://www.adl.org/resources/backgrounder/accelerationism | C77: /glossary/accelerationism/ | D77: Y | E77: =_xlfn.REGEXREPLACE(C77, "(.*)\/$", "https://extremismterms.adl.org\1") -> https://extremismterms.adl.org/glossary/accelerationism | F77: {=_xlfn.LET(_xlpm.rowNum,MATCH(E77,'glossaryterms-export'!C:C,0), IF(AND(NOT(ISBLANK(INDEX('glossaryterms-export'!H:H,_xlpm.rowNum))),ISBLANK(INDEX('glossaryterms-export'!I:I,_xlpm.rowNum))),"Ready to Fix",""))} | G77: 1490 | H77: 1316 | I77: 1.1322188 | J77: 22.298632 | K77: 3948
A78: 77 | C78: /glossary/hate-group/ | E78: =_xlfn.REGEXREPLACE(C78, "(.*)\/$", "https://extremismterms.adl.org\1") -> https://extremismterms.adl.org/glossary/hate-group | F78: {=_xlfn.LET(_xlpm.rowNum,MATCH(E78,'glossaryterms-export'!C:C,0), IF(AND(NOT(ISBLANK(INDEX('glossaryterms-export'!H:H,_xlpm.rowNum))),ISBLANK(INDEX('glossaryterms-export'!I:I,_xlpm.rowNum))),"Ready to Fix",""))} | G78: 1466 | H78: 1220 | I78: 1.2016393 | J78: 20.393443 | K78: 5699
A79: 78 | C79: /glossary/bishop-richard-williamson/ | E79: =_xlfn.REGEXREPLACE(C79, "(.*)\/$", "https://extremismterms.adl.org\1") -> https://extremismterms.adl.org/glossary/bishop-richard-williamson | F79: {=_xlfn.LET(_xlpm.rowNum,MATCH(E79,'glossaryterms-export'!C:C,0), IF(AND(NOT(ISBLANK(INDEX('glossaryterms-export'!H:H,_xlpm.rowNum))),ISBLANK(INDEX('glossaryterms-export'!I:I,_xlpm.rowNum))),"Ready to Fix",""))} -> Ready to Fix | G79: 1465 | H79: 1267 | I79: 1.1562747 | J79: 44.88161 | K79: 7698
A80: 79 | B80: /resources/article/nicholas-j-fuentes-five-things-know | C80: /glossary/nick-fuentes/ | D80: Y | E80: =_xlfn.REGEXREPLACE(C80, "(.*)\/$", "https://extremismterms.adl.org\1") -> https://extremismterms.adl.org/glossary/nick-fuentes | F80: {=_xlfn.LET(_xlpm.rowNum,MATCH(E80,'glossaryterms-export'!C:C,0), IF(AND(NOT(ISBLANK(INDEX('glossaryterms-export'!H:H,_xlpm.rowNum))),ISBLANK(INDEX('glossaryterms-export'!I:I,_xlpm.rowNum))),"Ready to Fix",""))} -> Ready to Fix | G80: 1464 | H80: 1275 | I80: 1.1482353 | J80: 17.472157 | K80: 3651
A81: 80 | C81: /glossary/new-world-order/ | E81: =_xlfn.REGEXREPLACE(C81, "(.*)\/$", "https://extremismterms.adl.org\1") -> https://extremismterms.adl.org/glossary/new-world-order | F81: {=_xlfn.LET(_xlpm.rowNum,MATCH(E81,'glossaryterms-export'!C:C,0), IF(AND(NOT(ISBLANK(INDEX('glossaryterms-export'!H:H,_xlpm.rowNum))),ISBLANK(INDEX('glossaryterms-export'!I:I,_xlpm.rowNum))),"Ready to Fix",""))} | G81: 1462 | H81: 1269 | I81: 1.1520883 | J81: 29.967691 | K81: 5640
A82: 81 | C82: /glossary/raven-folk-united/ | E82: =_xlfn.REGEXREPLACE(C82, "(.*)\/$", "https://extremismterms.adl.org\1") -> https://extremismterms.adl.org/glossary/raven-folk-united | F82: {=_xlfn.LET(_xlpm.rowNum,MATCH(E82,'glossaryterms-export'!C:C,0), IF(AND(NOT(ISBLANK(INDEX('glossaryterms-export'!H:H,_xlpm.rowNum))),ISBLANK(INDEX('glossaryterms-export'!I:I,_xlpm.rowNum))),"Ready to Fix",""))} | G82: 1455 | H82: 1248 | I82: 1.1658654 | J82: 23.60016 | K82: 4082
A83: 82 | B83: https://www.adl.org/resources/backgrounder/incels-involuntary-celibates | C83: /glossary/fakecel/ | E83: =_xlfn.REGEXREPLACE(C83, "(.*)\/$", "https://extremismterms.adl.org\1") -> https://extremismterms.adl.org/glossary/fakecel | F83: {=_xlfn.LET(_xlpm.rowNum,MATCH(E83,'glossaryterms-export'!C:C,0), IF(AND(NOT(ISBLANK(INDEX('glossaryterms-export'!H:H,_xlpm.rowNum))),ISBLANK(INDEX('glossaryterms-export'!I:I,_xlpm.rowNum))),"Ready to Fix",""))} | G83: 1412 | H83: 1248 | I83: 1.1314103 | J83: 16.071314 | K83: 5146
A84: 83 | C84: /glossary/wolves-vinland/ | E84: =_xlfn.REGEXREPLACE(C84, "(.*)\/$", "https://extremismterms.adl.org\1") -> https://extremismterms.adl.org/glossary/wolves-vinland | F84: {=_xlfn.LET(_xlpm.rowNum,MATCH(E84,'glossaryterms-export'!C:C,0), IF(AND(NOT(ISBLANK(INDEX('glossaryterms-export'!H:H,_xlpm.rowNum))),ISBLANK(INDEX('glossaryterms-export'!I:I,_xlpm.rowNum))),"Ready to Fix",""))} -> Ready to Fix | G84: 1367 | H84: 1159 | I84: 1.1794651 | J84: 25.861087 | K84: 3689
A85: 84 | C85: /resources/tools-and-strategies/education-glossary-terms/ | E85: =_xlfn.REGEXREPLACE(C85, "(.*)\/$", "https://extremismterms.adl.org\1") -> https://extremismterms.adl.org/resources/tools-and-strategies/education-glossary-terms | F85: {=_xlfn.LET(_xlpm.rowNum,MATCH(E85,'glossaryterms-export'!C:C,0), IF(AND(NOT(ISBLANK(INDEX('glossaryterms-export'!H:H,_xlpm.rowNum))),ISBLANK(INDEX('glossaryterms-export'!I:I,_xlpm.rowNum))),"Ready to Fix",""))} | G85: 1331 | H85: 1042 | I85: 1.2773512 | J85: 34.071977 | K85: 8707
A86: 85 | C86: /glossary/american-futurist/ | E86: =_xlfn.REGEXREPLACE(C86, "(.*)\/$", "https://extremismterms.adl.org\1") -> https://extremismterms.adl.org/glossary/american-futurist | F86: {=_xlfn.LET(_xlpm.rowNum,MATCH(E86,'glossaryterms-export'!C:C,0), IF(AND(NOT(ISBLANK(INDEX('glossaryterms-export'!H:H,_xlpm.rowNum))),ISBLANK(INDEX('glossaryterms-export'!I:I,_xlpm.rowNum))),"Ready to Fix",""))} | G86: 1300 | H86: 1147 | I86: 1.1333915 | J86: 17.014821 | K86: 6676
A87: 86 | B87: adl.org/resources/backgrounder/sovereign-citizen-movement-united-states | C87: /glossary/14th-amendment/ | D87: Y | E87: =_xlfn.REGEXREPLACE(C87, "(.*)\/$", "https://extremismterms.adl.org\1") -> https://extremismterms.adl.org/glossary/14th-amendment | F87: {=_xlfn.LET(_xlpm.rowNum,MATCH(E87,'glossaryterms-export'!C:C,0), IF(AND(NOT(ISBLANK(INDEX('glossaryterms-export'!H:H,_xlpm.rowNum))),ISBLANK(INDEX('glossaryterms-export'!I:I,_xlpm.rowNum))),"Ready to Fix",""))} | G87: 1282 | H87: 1211 | I87: 1.0586292 | J87: 22.477291 | K87: 4033
A88: 87 | C88: /glossary/nationalist-network/ | E88: =_xlfn.REGEXREPLACE(C88, "(.*)\/$", "https://extremismterms.adl.org\1") -> https://extremismterms.adl.org/glossary/nationalist-network | F88: {=_xlfn.LET(_xlpm.rowNum,MATCH(E88,'glossaryterms-export'!C:C,0), IF(AND(NOT(ISBLANK(INDEX('glossaryterms-export'!H:H,_xlpm.rowNum))),ISBLANK(INDEX('glossaryterms-export'!I:I,_xlpm.rowNum))),"Ready to Fix",""))} | G88: 1245 | H88: 1073 | I88: 1.1602982 | J88: 18.143523 | K88: 3539
A89: 88 | C89: /glossary/globalist/ | E89: =_xlfn.REGEXREPLACE(C89, "(.*)\/$", "https://extremismterms.adl.org\1") -> https://extremismterms.adl.org/glossary/globalist | F89: {=_xlfn.LET(_xlpm.rowNum,MATCH(E89,'glossaryterms-export'!C:C,0), IF(AND(NOT(ISBLANK(INDEX('glossaryterms-export'!H:H,_xlpm.rowNum))),ISBLANK(INDEX('glossaryterms-export'!I:I,_xlpm.rowNum))),"Ready to Fix",""))} -> Ready to Fix | G89: 1235 | H89: 1058 | I89: 1.1672968 | J89: 27.676749 | K89: 5392
A90: 89 | C90: /glossary/harold-hardy-carroll-lloyd/ | E90: =_xlfn.REGEXREPLACE(C90, "(.*)\/$", "https://extremismterms.adl.org\1") -> https://extremismterms.adl.org/glossary/harold-hardy-carroll-lloyd | F90: {=_xlfn.LET(_xlpm.rowNum,MATCH(E90,'glossaryterms-export'!C:C,0), IF(AND(NOT(ISBLANK(INDEX('glossaryterms-export'!H:H,_xlpm.rowNum))),ISBLANK(INDEX('glossaryterms-export'!I:I,_xlpm.rowNum))),"Ready to Fix",""))} | G90: 1196 | H90: 1124 | I90: 1.0640569 | J90: 15.837189 | K90: 2813
A91: 90 | C91: /glossary/pepe-frog/ | E91: =_xlfn.REGEXREPLACE(C91, "(.*)\/$", "https://extremismterms.adl.org\1") -> https://extremismterms.adl.org/glossary/pepe-frog | F91: {=_xlfn.LET(_xlpm.rowNum,MATCH(E91,'glossaryterms-export'!C:C,0), IF(AND(NOT(ISBLANK(INDEX('glossaryterms-export'!H:H,_xlpm.rowNum))),ISBLANK(INDEX('glossaryterms-export'!I:I,_xlpm.rowNum))),"Ready to Fix",""))} -> Ready to Fix | G91: 1189 | H91: 1029 | I91: 1.1554908 | J91: 16.284742 | K91: 2989
A92: 91 | C92: /glossary/khaybar-khaybar-ya-yahud/ | E92: =_xlfn.REGEXREPLACE(C92, "(.*)\/$", "https://extremismterms.adl.org\1") -> https://extremismterms.adl.org/glossary/khaybar-khaybar-ya-yahud | F92: {=_xlfn.LET(_xlpm.rowNum,MATCH(E92,'glossaryterms-export'!C:C,0), IF(AND(NOT(ISBLANK(INDEX('glossaryterms-export'!H:H,_xlpm.rowNum))),ISBLANK(INDEX('glossaryterms-export'!I:I,_xlpm.rowNum))),"Ready to Fix",""))} -> Ready to Fix | G92: 1188 | H92: 1012 | I92: 1.173913 | J92: 24.733202 | K92: 4280
A93: 92 | C93: /glossary/neo-nazi/ | E93: =_xlfn.REGEXREPLACE(C93, "(.*)\/$", "https://extremismterms.adl.org\1") -> https://extremismterms.adl.org/glossary/neo-nazi | F93: {=_xlfn.LET(_xlpm.rowNum,MATCH(E93,'glossaryterms-export'!C:C,0), IF(AND(NOT(ISBLANK(INDEX('glossaryterms-export'!H:H,_xlpm.rowNum))),ISBLANK(INDEX('glossaryterms-export'!I:I,_xlpm.rowNum))),"Ready to Fix",""))} | G93: 1187 | H93: 1056 | I93: 1.124053 | J93: 14.368371 | K93: 3144
A94: 93 | B94: https://www.adl.org/holocaust-denial-anatomy-antisemitic-conspiracy-theory | C94: /glossary/arthur-butz/ | D94: Y | E94: =_xlfn.REGEXREPLACE(C94, "(.*)\/$", "https://extremismterms.adl.org\1") -> https://extremismterms.adl.org/glossary/arthur-butz | F94: {=_xlfn.LET(_xlpm.rowNum,MATCH(E94,'glossaryterms-export'!C:C,0), IF(AND(NOT(ISBLANK(INDEX('glossaryterms-export'!H:H,_xlpm.rowNum))),ISBLANK(INDEX('glossaryterms-export'!I:I,_xlpm.rowNum))),"Ready to Fix",""))} | G94: 1182 | H94: 977 | I94: 1.209826 | J94: 42.451382 | K94: 6026
A95: 94 | B95: https://www.adl.org/resources/backgrounder/qanon | C95: /glossary/clay-clark/ | D95: Y | E95: =_xlfn.REGEXREPLACE(C95, "(.*)\/$", "https://extremismterms.adl.org\1") -> https://extremismterms.adl.org/glossary/clay-clark | F95: {=_xlfn.LET(_xlpm.rowNum,MATCH(E95,'glossaryterms-export'!C:C,0), IF(AND(NOT(ISBLANK(INDEX('glossaryterms-export'!H:H,_xlpm.rowNum))),ISBLANK(INDEX('glossaryterms-export'!I:I,_xlpm.rowNum))),"Ready to Fix",""))} | G95: 1163 | H95: 974 | I95: 1.1940452 | J95: 25.054415 | K95: 4730
A96: 95 | B96: https://adl.org/resources/backgrounder/christian-identity-movement | C96: /glossary/christian-identity-movement/ | D96: Y | E96: =_xlfn.REGEXREPLACE(C96, "(.*)\/$", "https://extremismterms.adl.org\1") -> https://extremismterms.adl.org/glossary/christian-identity-movement | F96: {=_xlfn.LET(_xlpm.rowNum,MATCH(E96,'glossaryterms-export'!C:C,0), IF(AND(NOT(ISBLANK(INDEX('glossaryterms-export'!H:H,_xlpm.rowNum))),ISBLANK(INDEX('glossaryterms-export'!I:I,_xlpm.rowNum))),"Ready to Fix",""))} -> Ready to Fix | G96: 1152 | H96: 972 | I96: 1.1851852 | J96: 34.548354 | K96: 3387
A97: 96 | C97: /glossary/western-chauvinism/ | E97: =_xlfn.REGEXREPLACE(C97, "(.*)\/$", "https://extremismterms.adl.org\1") -> https://extremismterms.adl.org/glossary/western-chauvinism | F97: {=_xlfn.LET(_xlpm.rowNum,MATCH(E97,'glossaryterms-export'!C:C,0), IF(AND(NOT(ISBLANK(INDEX('glossaryterms-export'!H:H,_xlpm.rowNum))),ISBLANK(INDEX('glossaryterms-export'!I:I,_xlpm.rowNum))),"Ready to Fix",""))} | G97: 1105 | H97: 942 | I97: 1.1730361 | J97: 22.072187 | K97: 4251
A98: 97 | C98: /glossary/hannah-pearl-davis/ | E98: =_xlfn.REGEXREPLACE(C98, "(.*)\/$", "https://extremismterms.adl.org\1") -> https://extremismterms.adl.org/glossary/hannah-pearl-davis | F98: {=_xlfn.LET(_xlpm.rowNum,MATCH(E98,'glossaryterms-export'!C:C,0), IF(AND(NOT(ISBLANK(INDEX('glossaryterms-export'!H:H,_xlpm.rowNum))),ISBLANK(INDEX('glossaryterms-export'!I:I,_xlpm.rowNum))),"Ready to Fix",""))} | G98: 1088 | H98: 988 | I98: 1.1012146 | J98: 29.321862 | K98: 4380
A99: 98 | C99: /glossary/ucc-1-308-and-ucc-1-207/ | E99: =_xlfn.REGEXREPLACE(C99, "(.*)\/$", "https://extremismterms.adl.org\1") -> https://extremismterms.adl.org/glossary/ucc-1-308-and-ucc-1-207 | F99: {=_xlfn.LET(_xlpm.rowNum,MATCH(E99,'glossaryterms-export'!C:C,0), IF(AND(NOT(ISBLANK(INDEX('glossaryterms-export'!H:H,_xlpm.rowNum))),ISBLANK(INDEX('glossaryterms-export'!I:I,_xlpm.rowNum))),"Ready to Fix",""))} -> Ready to Fix | G99: 1086 | H99: 964 | I99: 1.126556 | J99: 42.208506 | K99: 4714
A100: 99 | C100: /glossary/mkultra/ | E100: =_xlfn.REGEXREPLACE(C100, "(.*)\/$", "https://extremismterms.adl.org\1") -> https://extremismterms.adl.org/glossary/mkultra | F100: {=_xlfn.LET(_xlpm.rowNum,MATCH(E100,'glossaryterms-export'!C:C,0), IF(AND(NOT(ISBLANK(INDEX('glossaryterms-export'!H:H,_xlpm.rowNum))),ISBLANK(INDEX('glossaryterms-export'!I:I,_xlpm.rowNum))),"Ready to Fix",""))} | G100: 1061 | H100: 902 | I100: 1.1762749 | J100: 22.845898 | K100: 4401
...

Sheet All ADL.org Backgrounders
A1: title | B1: nid | C1: url
A2: The "Kosher Tax" Hoax: Anti-Semitic Recipe for Hate | B2: 30698 | C2: https://adl.ddev.site/resources/backgrounder/kosher-tax-hoax-anti-semitic-recipe-hate
A3: Jewish "Control" of the Federal Reserve: A Classic Antisemitic Myth | B3: 30699 | C3: https://adl.ddev.site/resources/backgrounder/jewish-control-federal-reserve-classic-antisemitic-myth
A4: The International Jew: 1920s Antisemitism Revived Online | B4: 30700 | C4: https://adl.ddev.site/resources/backgrounder/international-jew-1920s-antisemitism-revived-online
A5: Brown v. Board of Education | B5: 30702 | C5: https://adl.ddev.site/resources/backgrounder/brown-v-board-education
A6: Civil Rights Act of 1964 | B6: 30703 | C6: https://adl.ddev.site/resources/backgrounder/civil-rights-act-1964
A7: The Council on American Islamic Relations (CAIR) | B7: 30704 | C7: https://www.adl.org/resources/backgrounder/council-american-islamic-relations-cair
A8: From "Little Rock Nine" to Today | B8: 30713 | C8: https://adl.ddev.site/resources/backgrounder/little-rock-nine-today
A9: Oath Keepers and Three %ers Part of Growing Anti-Government Movement | B9: 30717 | C9: https://adl.ddev.site/resources/backgrounder/oath-keepers-and-three-ers-part-growing-anti-government-movement
A10: Glossary of Key Terms and Events in Israel's History: Israeli-Arab / Israeli-Palestinian Conflict | B10: 30722 | C10: https://adl.ddev.site/resources/backgrounder/glossary-key-terms-and-events-israels-history-israeli-arab-israeli
A11: Farrakhan: In His Own Words | B11: 30728 | C11: https://adl.ddev.site/resources/backgrounder/farrakhan-his-own-words
A12: Blood Libel: A False, Incendiary Claim Against Jews | B12: 30729 | C12: https://adl.ddev.site/resources/backgrounder/blood-libel-false-incendiary-claim-against-jews
A13: Primer on the First Amendment & Religious Freedom | B13: 30732 | C13: https://adl.ddev.site/resources/backgrounder/primer-first-amendment-religious-freedom
... A213: Los hutÃ­es: una larga tradiciÃ³n de antisemitismo y odio a Israel | B213: 91807 | C213: https://www.adl.org/es/resources/backgrounder/los-huties-una-larga-tradicion-de-antisemitismo-y-odio-israel
A214: 764 | B214: 92206 | C214: https://www.adl.org/resources/backgrounder/764
A215: Plan Andinia | B215: 92372 | C215: https://adl.ddev.site/es/resources/backgrounder/plan-andinia
A216: Iranian Supreme Leader Ayatollah Khamenei In His Own Words | B216: 92705 | C216: https://adl.ddev.site/resources/backgrounder/iranian-supreme-leader-ayatollah-khamenei-his-own-words
A217: El lÃ­der supremo iranÃ­, el ayatolÃ¡ Jamenei, en sus propias palabras | B217: 92712 | C217: https://adl.ddev.site/es/resources/backgrounder/el-lider-supremo-irani-el-ayatola-jamenei-en-sus-propias-palabras
A218: Slogan: Free Palestine | B218: 92733 | C218: https://adl.ddev.site/resources/backgrounder/slogan-free-palestine
A219: Abraham Accords | B219: 92734 | C219: https://adl.ddev.site/resources/backgrounder/abraham-accords
A220: The International Union of Muslim Scholars (IUMS) in Its Own Words | B220: 92792 | C220: https://adl.ddev.site/resources/backgrounder/international-union-muslim-scholars-iums-its-own-words
A221: Eslogan: Palestina libre | B221: 92804 | C221: https://adl.ddev.site/es/resources/backgrounder/eslogan-palestina-libre
A222: Acuerdos de Abraham | B222: 92805 | C222: https://adl.ddev.site/es/resources/backgrounder/acuerdos-de-abraham
A223: The Party for Socialism and Liberation (PSL) | B223: 92842 | C223: https://www.adl.org/resources/backgrounder/party-socialism-and-liberation-psl
A224: Understanding and Countering Soft and Shadow Boycotts of Israel | B224: 93187 | C224: https://adl.ddev.site/resources/backgrounder/understanding-and-countering-soft-and-shadow-boycotts-israel
A225: Sobre la definiciÃ³n de trabajo del antisemitismo de la IHRA | B225: 93196 | C225: https://adl.ddev.site/es/resources/backgrounder/sobre-la-definicion-de-trabajo-del-antisemitismo-de-la-ihra
A226: Faculty and Staff for Justice in Palestine (FSJP) | B226: 93229 | C226: https://www.adl.org/resources/backgrounder/faculty-and-staff-justice-palestine-fsjp

Sheet glossaryterms-export
B1: Title | C1: URL | D1: Category | E1: Ideology | F1: Summary | G1: URL to be Redirected to (FL/Rebecca/SME First Pass) | H1: URL to be Redirected to (finalized) | I1: Redirect Put in Place? | J1: Notes | K1: PRIORITY | L1: Note
A2: 681 | B2: Looksmaxxing | C2: https://extremismterms.adl.org/glossary/looksmaxxing | D2: Tactics, Key Concepts / Definitions | E2: Single-issue | F2: Looksmaxxing refers to any attempts made by incels to improve upon their physical appearance. These strategies range from haircuts and new clothes, taking steroids and going to the gym all the way up to cosmetic surgery. | G2: https://www.adl.org/resources/backgrounder/incels-involuntary-celibates | H2: https://www.adl.org/resources/backgrounder/incels-involuntary-celibates | I2: Y | K2: low | L2: Incel/ misogyny terms/phrases
A3: 854 | B3: White supremacist (physical) propaganda | C3: https://extremismterms.adl.org/glossary/white-supremacist-physical-propaganda | D3: Tactics | E3: White supremacist, Right-wing, Antisemitism | F3: Physical white supremacist propaganda includes distributions of physical media like fliers, posters, stickers, leaflets, banners and graffiti. The goal is to maximize media and online attention, while limiting the risk of individual exposure, negative media coverage, arrests and public backlash that often accompany public white supremacist events.
A4: 49779 | B4: Q clock | C4: https://adl.org/glossary/q-clock | D4: Tactics | E4: Right-wing | F4: The Q clock is a tool used by QAnon followers to "prove" that Q has predicted future events. The Q clock consists of a standard clock surrounded by a line spiraling outwards, which features a series of dated points. Each point forms a "second" on the clock, and a shaded date indicates that Q posted a drop(s) on that date. To "read" the clock, QAnon followers draw a line from today's date on the spiral to the center of the clock, checking for any Q drops on shaded dates that the line intersects and decoding their meaning. The clock can also be "mirrored" by continuing to draw a line through to the other side of the clock, intersecting additional shaded dates and drops that can be decoded. The Q clock can only be used to confirm that Q predicted a future event in a prior drop; it cannot be used by QAnon followers to predict future events. | G4: https://www.adl.org/resources/backgrounder/qanon | H4: https://www.adl.org/resources/backgrounder/qanon | I4: Y | K4: low | L4: conspiracy (QAnon)
A5: 82979 | B5: Red ink thumbprints/fingerprints | C5: https://extremismterms.adl.org/glossary/red-ink-thumbprintsfingerprints | D5: Tactics | E5: Right Wing (Anti-Government) | F5: Some sovereign citizens believe they must place a thumbprint or fingerprint next to their signature on a document for it to be valid. Most, though not all, who hold such beliefs further claim that the signature and fingerprint must be in red ink.The origins of the sovereign citizen thumbprint idea date back to the late 1980s, though it only became popular in the 1990s. In some societies at some points in history, such prints were used as signatures or were required to accompany signatures.
A6: 71 | B6: Black Bloc Tactics | C6: https://extremismterms.adl.org/glossary/black-bloc-tactics | D6: Tactics | E6: Left-wing | F6: Black bloc tactics are often employed by militant antifa adherents at protests. Participants dressed in all black will operate as a unified force. Tactics include arming themselves with riot shields and positioning themselves at the front while others behind them move "like water." | G6: https://www.adl.org/resources/backgrounder/who-are-antifa | H6: https://www.adl.org/resources/backgrounder/who-are-antifa | K6: medium | L6: left wing terms/symbols
A7: 685 | B7: Media Jihad | C7: https://extremismterms.adl.org/glossary/media-jihad | D7: Tactics | E7: Islamist, Antisemitism | F7: "Media jihad" refers to an ISIS innovation in the Islamist terrorist sphere heavily emphasizing online media and appealing propaganda as a means of recruiting foreign fighters and spreading its message. To this end, ISIS recruiters often emphasize that "media jihad," creating and spreading ISIS propaganda online, is just as effective a method of supporting the caliphate as traveling to conflict zones.
A8: 700 | B8: Nutella and Kittens | C8: https://extremismterms.adl.org/glossary/nutella-and-kittens | D8: Tactics | E8: Islamist, Antisemitism | F8: Nutella and kittens was among ISIS's more inventive and disturbing media tactics. In 2015, the group paired calls to join the Islamic State with innocuous images that were popular on the internet, including pictures of kittens or jars of Nutella. One New Jersey-based ISIS recruiter even went by the online nickname "Umm Nutella," meaning "Mother of Nutella." Though it is unclear whether this tactic was effective at increasing recruitment, it generated a great deal of attention for ISIS online.
A9: 713 | B9: Paper Terrorism | C9: https://extremismterms.adl.org/glossary/paper-terrorism | D9: Tactics | E9: Anti-government, Right-wing | F9: "Paper terrorism" is a term given to a range of tactics developed by the sovereign citizen movement to use against their perceived enemies. These tactics typically involve the filing of bogus legal documents or the misuse of legal documents in a way designed to harass, retaliate against or harm police, government officials and others. Common paper terrorism tactics include bogus liens, false IRS 1099 forms, false involuntary bankruptcies and false criminal complaints, among others. | G9: https://www.adl.org/resources/backgrounder/sovereign-citizen-movement-united-states | H9: https://www.adl.org/resources/backgrounder/sovereign-citizen-movement-united-states | I9: Y | K9: Low | L9: sovereign citizen term (solution create an article with a list of sovereign citizen groups and terms?)
A10: 92203 | B10: Blood Signs / Blood Signing | C10: https://extremismterms.adl.org/glossary/blood-signs-blood-signing | D10: Tactics | F10: Blood signing refers to the practice of coercing a victim to write their abuser‚Äôs name or aliases on their own body or other surfaces using either their own blood or animal blood.¬†¬†764 members use ‚Äúblood signs‚Äù to demonstrate their ‚Äúownership‚Äù over their victim(s) and obtain further influence within the network. | G10: https://www.adl.org/resources/backgrounder/764 | H10: https://www.adl.org/resources/backgrounder/764 | I10: Y | K10: medium | L10: nihilistic term/activity
A11: 92202 | B11: Cut Signs / Cut Signing | C11: https://extremismterms.adl.org/glossary/cut-signs-cut-signing | D11: Tactics | F11: Cut signing refers to the practice of coercing a victim to carve their abuser‚Äôs name or aliases into their own bodies.764 members use ‚Äúcut signs‚Äù to demonstrate their ‚Äúownership‚Äù over their victim(s) and obtain further influence within the network. | G11: https://www.adl.org/resources/backgrounder/764 | H11: https://www.adl.org/resources/backgrounder/764 | I11: Y | K11: medium | L11: nihlistic term/activity
A12: 92204 | B12: Fan Signs / Fan Signing | C12: https://extremismterms.adl.org/glossary/fan-signs-fan-signing | D12: Tactics | F12: Fan signing refers to the practice of coercing a victim to write their abuser‚Äôs name or aliases on their own body. In some cases, victims may also be encouraged to vandalize private property with the abuser‚Äôs name.764 members use ‚Äúfan signs‚Äù to demonstrate their ‚Äúownership‚Äù over their victim(s) and obtain further influence within the network. | G12: https://www.adl.org/resources/backgrounder/764 | H12: https://www.adl.org/resources/backgrounder/764 | I12: Y | K12: medium | L12: nihlistic term/activity
A13: 92201 | B13: Lorebook | C13: https://extremismterms.adl.org/glossary/lorebook | D13: Tactics | F13: Lorebooks are digital archives compiled by 764 members to extort their victims. They often include sexually explicit content, images or videos of self-harm, private messages between the victim and their abuser and other personal information, such as the victim‚Äôs full name, address and relatives.764 members use lorebooks to extort their victims, threatening to share them with a victim‚Äôs family or friends unless their demands are met. Many of these lorebooks, which typically feature minors, are also posted publicly in 764 chats so that other members can harass the victim. | G13: https://www.adl.org/resources/backgrounder/764 | H13: https://www.adl.org/resources/backgrounder/764 | I13: Y | K13: medium | L13: nihlistic term/activity
A14: 566 | B14: 14/23 | C14: https://extremismterms.adl.org/glossary/1423 | D14: Slogans / Code words, Numbers / Symbols | E14: White supremacist, Right-wing, Antisemitism | F14: 14/23 is a numeric code associated with the Southern Brotherhood, a white supremacist prison gang in Alabama. Fourteen is a reference to the 14 words, and 23 refers to the 23 rules members must follow. | G14: https://www.adl.org/resources/hate-symbol/1423 | H14: https://www.adl.org/resources/hate-symbol/1423 | J14: Marilyn | K14: low | L14: in HATE SYMBOLS DATABASE (or add)
A15: 630 | B15: Bowl Gang /Bowlwaffen/Bowlwaffen Division/The Bowl Patrol | C15: https://extremismterms.adl.org/glossary/bowl-gang-bowlwaffenbowlwaffen-divisionthe-bowl-patrol | D15: Slogans / Code words, Numbers / Symbols | E15: White supremacist, Right-wing, Antisemitism | F15: "Bowl Gang," "Bowlwaffen," "Bowlwaffen Division," and "the Bowl Patrol" are phrases and symbology used by supporters of white supremacist Dylann Roof who was convicted of murdering nine African-Americans in a racially motivated shooting spree at the Emanuel African Methodist Episcopal Church in Charleston, South Carolina, in 2015. The "Bowl" references Roof"s bowl-shaped haircut. Accelerationist groups consider Dylann Roof a "saint" and idolize his murderous actions, calling for others to emulate his racist murders. | G15: https://www.adl.org/resources/backgrounder/accelerationism | H15: https://www.adl.org/resources/backgrounder/accelerationism | I15: Y | K15: low | L15: in HATE SYMBOLS DATABASE (or add)
A16: 563 | B16: 13/90 | C16: https://extremismterms.adl.org/glossary/1390 | D16: Slogans / Code words, Numbers / Symbols | E16: White supremacist, Right-wing | F16: 13/90 is a numeric code phrase used by white supremacists as a shorthand reference to a common racist claim about alleged Black violence. The number 13 refers to the purported percentage of the U.S. population that is Black. The number 90 is a fabricated "percentage" of violent crimes committed by Black people. | G16: https://www.adl.org/resources/hate-symbol/1352-1390 | H16: https://www.adl.org/resources/hate-symbol/1352-1390 | J16: Marilyn | K16: low | L16: in HATE SYMBOLS DATABASE (or add)
A17: 813 | B17: The Great Awakening | C17: https://extremismterms.adl.org/glossary/great-awakening | D17: Slogans / Code words, Key Concepts / Definitions, Conspiracy Theories | E17: White supremacist, Right-wing, Antisemitism | F17: "The Great Awakening" refers to Q's dissemination of information, which began in October 2017. QAnon adherents believe that they are part of a vast intelligence operation designed to slowly awaken the American people to the truth about the Deep State. | G17: https://www.adl.org/resources/backgrounder/qanon | H17: https://www.adl.org/resources/backgrounder/qanon | I17: Y | L17: conspiracy
A18: 649 | B18: Day of the Rope | C18: https://extremismterms.adl.org/glossary/day-rope | D18: Slogans / Code words, Key Concepts / Definitions | E18: White supremacist, Right-wing, Antisemitism | F18: Day of the Rope is a white supremacist concept that draws on fictional mass murders of "race traitors" in The Turner Diaries. The phrase is sometimes shortened to a hashtag or "dotr," or written out as "The Day of the Rope is coming" to convey a threat of white revolution or targeted violence. | G18: https://www.adl.org/resources/hate-symbol/day-rope | H18: https://www.adl.org/resources/hate-symbol/day-rope | K18: low | L18: in HATE SYMBOLS DATABASE (or add)
A19: 742 | B19: Race traitor | C19: https://extremismterms.adl.org/glossary/race-traitor | D19: Slogans / Code words, Key Concepts / Definitions | E19: White supremacist, Right-wing, Antisemitism | F19: "Race traitor" is a term used by white supremacists to refer to people involved in multi-racial relationships, as well as other white people perceived by white supremacists to be acting against the best interests of the white race. | K19: low | L19: in HATE SYMBOLS DATABASE (or add)
A20: 743 | B20: Racial Holy War/RAHOWA | C20: https://extremismterms.adl.org/glossary/racial-holy-warrahowa | D20: Slogans / Code words, Key Concepts / Definitions | E20: White supremacist, Right-wing, Antisemitism | F20: RAHOWA is an acronym for "Racial Holy War" created by the Creativity Movement, a white supremacist pseudo-religion, as a rallying cry for the white supremacist cause. | G20: https://www.adl.org/resources/hate-symbol/rahowa | H20: https://www.adl.org/resources/hate-symbol/rahowa | K20: low | L20: in HATE SYMBOLS DATABASE (or add)
A21: 639 | B21: Chad | C21: https://extremismterms.adl.org/glossary/chad | D21: Slogans / Code words, Key Concepts / Definitions | E21: Single-issue | F21: Chad is a term referring to the archetypal "anti-incel:" a white, straight male with Aryan features and other "desirable" physical traits. Chads are simultaneously despised and revered by incels who believe that all women inherently desire these men. | G21: https://www.adl.org/resources/backgrounder/incels-involuntary-celibates | H21: https://www.adl.org/resources/backgrounder/incels-involuntary-celibates | I21: Y
A22: 43297 | B22: Grooming/Groomers | C22: https://extremismterms.adl.org/glossary/groominggroomers | D22: Slogans / Code words, Key Concepts / Definitions | E22: Single-issue | F22: Grooming refers to behaviors used by abusers to build relationships and trust with children or young people to aid in manipulating, exploiting and abusing them. The term has been appropriated and weaponized by anti-LGBTQ+ bigots who falsely imply or claim that members of the LGBTQ+ community are pedophiles and are ‚Äúgrooming‚Äù children by discussing issues related to sexual orientation and gender identity. | G22: https://www.adl.org/resources/article/what-grooming-truth-behind-dangerous-bigoted-lie-targeting-lgbtq-community | H22: https://www.adl.org/resources/article/what-grooming-truth-behind-dangerous-bigoted-lie-targeting-lgbtq-community
A23: 839 | B23: Volcel | C23: https://extremismterms.adl.org/glossary/volcel | D23: Slogans / Code words, Key Concepts / Definitions | E23: Single-issue | F23: Also known as "fakecel," the term "volcel" is used within the incel subculture to describe a person who is voluntarily celibate and therefore does not fit the criteria to be an incel. | G23: https://www.adl.org/resources/backgrounder/incels-involuntary-celibates | H23: https://www.adl.org/resources/backgrounder/incels-involuntary-celibates | I23: Y | K23: low | L23: Incel/ misogyny terms/phrases
A24: 68856 | B24: Cultural Marxism | C24: https://extremismterms.adl.org/glossary/cultural-marxism | D24: Slogans / Code words, Key Concepts / Definitions | E24: Right-wing | F24: ‚ÄúCultural Marxism‚Äù is a term used typically by right-wing ideologues to attack an array of ideas and concepts they oppose, including multiculturalism, globalism, feminism and LGBTQ+ rights, among others. The term often functions as an antisemitic dog whistle or codeword. Promoters of the term typically invoke a conspiracy theory that falsely claims such progressive ideas originated with the so-called Frankfurt School, a leftist intellectual collective active in Germany between the two World Wars. Exploiting the fact that a number of the Frankfurt School intellectuals were Jewish, antisemitic versions of this conspiracy theory link the Frankfurt School, and thus ‚Äúcultural Marxism‚Äù itself, to Jews, claiming that Jews seek to subvert and weaken Western (and Christian) society by imposing their left-wing and politically correct (or ‚Äúwoke‚Äù) views. Antisemites also use the term to reinforce their longstanding antisemitic trope that Communism is ‚ÄúJewish.‚Äù
A25: 844 | B25: Western Chauvinism | C25: https://extremismterms.adl.org/glossary/western-chauvinism | D25: Slogans / Code words, Key Concepts / Definitions | E25: Right-wing | F25: Western chauvinism is a term that emphasizes the unabashed embrace and belief in the superiority of the western world, with an ethnocentric focus on maintaining a "western culture." Members of the Proud Boys often refer to themselves as "western chauvinists," and part of the Proud Boys' indoctrination ritual includes the use of the phrase, "I am a proud western chauvinist and I refuse to apologize for creating the modern world." | G25: https://www.adl.org/resources/backgrounder/proud-boys | H25: https://www.adl.org/resources/backgrounder/proud-boys | I25: Y
A26: 91823 | B26: Zionist Entity | C26: https://extremismterms.adl.org/glossary/zionist-entity | D26: Slogans / Code words, Key Concepts / Definitions | E26: Left Wing, Islamist | F26: ‚ÄúZionist entity‚Äù is a derogatory term for Israel designed to deny Israel‚Äôs legitimacy. The term emerged by the 1960s, used by Arab leaders in the Middle East who needed to refer to Israel but did not want to acknowledge its existence as a nation. Instead, they referred to Israel using language such as ‚Äúthe Zionist entity existing in Palestine.‚Äù Opponents of Israel continue to use the term today. In May 2025, after a gunman killed two Israeli Embassy staff members in Washington, D.C., Masar Badil‚Äîa transnational anti-Israel organization with ties to the terror-affiliated group Samidoun‚Äîresponded by saying that the attack was ‚Äúa natural consequence of the Zionist entity‚Äôs crimes in the Gaza Strip.‚Äù¬†The term ‚ÄúZionist entity‚Äù has spread to opponents and detractors of Israel more broadly, including within the United States. Usage of the term in the United States began as early as 1970. Today, it is primarily used by far left and anti-Israel groups and individuals, such as Students for Justice in Palestine, Within Our Lifetime, Palestinian Youth Movement, and PAL-Awda. Abroad, the term has also frequently been used by Iran‚Äôs Supreme Leader Ali Khamenei and other regime officials, as well as by the former leader of the terrorist group Hezbollah, Hassan Nasrallah. | G26: Mentioned and defined sort of here: https://www.adl.org/resources/article/healthcare-workers-palestine-hcw4p-what-you-need-know
A27: 799 | B27: Synagogue of Satan | C27: https://extremismterms.adl.org/glossary/synagogue-satan | D27: Slogans / Code words, Key Concepts / Definitions | E27: Antisemitism | F27: "Synagogue of Satan" is a derogatory term used by various antisemites ‚Äî such as the Nation of Islam, extremist sects of the Black Hebrew Israelite movement and many extremists who identify as Christians ‚Äî to refer to Jews and Judaism. The phrase is a reference to Revelation 2:9 and 3:9 in the Bible. | G27: No alternative source (MLM) | K27: priority | L27: antisemitic term/symbol/conspiracy
A28: 77 | B28: Blue-Eyed Devils | C28: https://extremismterms.adl.org/glossary/blue-eyed-devils | D28: Slogans / Code words, Groups / Movements | E28: White supremacist, Right-wing, Antisemitism | F28: The term "blue-eyed devil" is a racial epithet that originated in Asia, directed against people of European ancestry. Some white supremacists have adopted the term in recent decades and may refer to themselves as blue-eyed devils. A mid-1990s white power/Rock Against Communism (RAC) band from Delaware was also named Blue-Eyed Devils. The band is held in high regards by fellow white supremacists; many get tattoos of the band's distinctive logo, which is a man pointing a gun out of a rounded Celtic cross. | G28: https://www.adl.org/resources/hate-symbol/blue-eyed-devils | H28: https://www.adl.org/resources/hate-symbol/blue-eyed-devils | K28: low | L28: in HATE SYMBOLS DATABASE (or add)
A29: 773 | B29: Save the/our Children | C29: https://extremismterms.adl.org/glossary/save-theour-children | D29: Slogans / Code words, Conspiracy Theories, Key Concepts / Definitions | E29: Right-wing | F29: "Save the children" is a QAnon rallying cry often used as a hashtag on social media. QAnon borrowed this hashtag from a legitimate human-trafficking campaign to spread the baseless claim that pedophiles are kidnapping children off the streets and that mole/tunnel children are trafficked underground. Concerned people then spread the message using the hashtag, often unaware they are spreading a QAnon conspiracy. | G29: https://www.adl.org/resources/backgrounder/qanon | H29: https://www.adl.org/resources/backgrounder/qanon | I29: Y | K29: low | L29: conspiracy (QAnon)
A30: 867 | B30: Z.O.G. (Zionist Occupied Government) | C30: https://extremismterms.adl.org/glossary/zog-zionist-occupied-government | D30: Slogans / Code words, Conspiracy Theories | E30: White supremacist, Right-wing, Antisemitism | F30: Z.O.G. is an antisemitic acronym for "Zionist Occupied Government," which reflects the belief, often held by white supremacists and other antisemitic conspiracy theorists, that the U.S. government is controlled by Jews. This has resulted in white supremacist slogans such as "Smash ZOG," "Kill ZOG" and "Death to ZOG." | G30: https://www.adl.org/resources/hate-symbol/zog | H30: https://www.adl.org/resources/hate-symbol/zog | I30: Y | K30: priority | L30: antisemitic term/symbol/conspiracy
A31: 569 | B31: 17Anon | C31: https://extremismterms.adl.org/glossary/17anon | D31: Slogans / Code words, Conspiracy Theories | E31: Right-wing | F31: 17Anon is another name for QAnon, as Q is the seventeenth letter of the alphabet. The phrase is used to bypass blocking algorithms on social media. | G31: https://www.adl.org/resources/backgrounder/qanon | H31: https://www.adl.org/resources/backgrounder/qanon | I31: Y | J31: 17Anon is not mentioned in the QAnon backgrounder and should be added. Marilyn
A32: 740 | B32: Q sent me/us | C32: https://extremismterms.adl.org/glossary/q-sent-meus | D32: Slogans / Code words, Conspiracy Theories | E32: Right-wing | F32: "Q sent me" or "Q sent us" is a phrase used by QAnon adherents to express their allegiance to Q and their association with the army of digital soldiers. | G32: https://www.adl.org/resources/backgrounder/qanon | H32: https://www.adl.org/resources/backgrounder/qanon | I32: Y | K32: low | L32: conspiracy (QAnon)
A33: 3 | B33: "Pestilence from Heaven" | C33: https://extremismterms.adl.org/glossary/pestilence-heaven | D33: Slogans / Code words, Conspiracy Theories | E33: Antisemitism | F33: "Pestilence from Heaven" is a phrase used by the Nation of Islam to describe the coronavirus pandemic, with some specifically blaming Jews and Israel for causing the "pestilence." | G33: https://www.adl.org/resources/profile/nation-islam | H33: https://www.adl.org/resources/profile/nation-islam | J33: Marilyn
A34: 2 | B34: "Good Habits Bad Boys" | C34: https://extremismterms.adl.org/glossary/good-habits-bad-boys | D34: Slogans / Code words | E34: White supremacist, Right-wing, Antisemitism | F34: "Good habits bad boys" is the unofficial slogan of the Rise Above Movement (R.A.M.). It is often used in R.A.M. and R.A.M.-affilitated propaganda and clothing. | G34: https://www.adl.org/resources/backgrounder/rise-above-movement-ram | H34: https://www.adl.org/resources/backgrounder/rise-above-movement-ram | I34: Y | J34: Although this term is associated with the Rise Above Movement, it isn't in the current backgrounder and will have to be added. Marilyn | K34: low | L34: in HATE SYMBOLS DATABASE (or add)
A35: 4 | B35: "White Boy Summer" | C35: https://extremismterms.adl.org/glossary/white-boy-summer | D35: Slogans / Code words | E35: White supremacist, Right-wing, Antisemitism | F35: "White Boy Summer" was originally a Chet Hanks song released in March 2021, but was co-opted by white supremacists for their own purposes by layering on exclusionary messaging and using it as a call for action. | G35: https://www.adl.org/resources/article/white-boy-summer-meme-mobilization | H35: https://www.adl.org/resources/article/white-boy-summer-meme-mobilization | J35: Marilyn | K35: low | L35: in HATE SYMBOLS DATABASE (or add)
A36: 865 | B36: "You will not replace us" | C36: https://extremismterms.adl.org/glossary/you-will-not-replace-us | D36: Slogans / Code words | E36: White supremacist, Right-wing, Antisemitism | F36: "You will not replace us" is a slogan used by white supremacists that reflects the belief that without immediate action, the white race is doomed to extinction by an alleged "rising tide of color" purportedly controlled and manipulated by Jews. It is also a substitute for the "14 words" white supremacist motto. | G36: https://www.adl.org/resources/hate-symbol/you-will-not-replace-us | H36: https://www.adl.org/resources/hate-symbol/you-will-not-replace-us | J36: Marilyn | K36: low | L36: in HATE SYMBOLS DATABASE (or add)
A37: 565 | B37: 14 words | C37: https://extremismterms.adl.org/glossary/14-words | D37: Slogans / Code words | E37: White supremacist, Right-wing, Antisemitism | F37: 14 words is a popular white supremacist slogan penned by white supremacist and convicted terrorist David Lane: "We must secure the existence of our people and a future for white children.' | G37: https://www.adl.org/resources/hate-symbol/14-words | H37: https://www.adl.org/resources/hate-symbol/14-words | J37: Marilyn | K37: low | L37: in HATE SYMBOLS DATABASE (or add)
A38: 574 | B38: 23 (Hand Sign) | C38: https://extremismterms.adl.org/glossary/23-hand-sign | D38: Slogans / Code words | E38: White supremacist, Right-wing, Antisemitism | F38: This hand sign, in which one hand shows two fingers, and the other three, represents the number 23. Some white supremacists use this hand sign to represent the 23rd letter of the alphabet: W for white. | G38: https://www.adl.org/resources/hate-symbol/23-hand-sign | H38: https://www.adl.org/resources/hate-symbol/23-hand-sign | J38: Marilyn | K38: low | L38: in HATE SYMBOLS DATABASE (or add)
A39: 6 | B39: 6 Million Wasn't Enough (6MWE) | C39: https://extremismterms.adl.org/glossary/6-million-wasnt-enough-6mwe | D39: Slogans / Code words | E39: White supremacist, Right-wing, Antisemitism | F39: 6 Million Wasn't Enough (sometimes abbreviated to 6MWE) is an antisemitic phrase used by white supremacists which laments that only six million Jews murdered during the Holocaust. | G39: https://www.adl.org/resources/article/proud-boys-bigotry-full-display | H39: No resource outside Glossary (MLM) | J39: We could link here: https://www.adl.org/resources/article/proud-boys-bigotry-full-display, which references the term, but the term itself is not explicitly Proud Boys (MLM). | K39: priority | L39: add to innocuous phrase article
A40: 585 | B40: ACAB (All Cops Are Bastards) | C40: https://extremismterms.adl.org/glossary/acab-all-cops-are-bastards | D40: Slogans / Code words | E40: White supremacist, Right-wing, Antisemitism | F40: The acronym ACAB stands for 'All Cops Are Bastards' and is a slogan of long standing within skinhead subculture, which borrowed it from the punk subculture. Because non-racist skinheads (including "traditional" skinheads and anti-racist skinheads) may use this acronym as well as racist skinheads, it should be carefully judged in the context in which it appears. | G40: https://www.adl.org/resources/hate-symbol/acab | H40: https://www.adl.org/resources/hate-symbol/acab | J40: Marilyn | K40: low | L40: in HATE SYMBOLS DATABASE (or add)
A41: 593 | B41: AKIA | C41: https://extremismterms.adl.org/glossary/akia | D41: Slogans / Code words | E41: White supremacist, Right-wing, Antisemitism | F41: AKIA is Ku Klux Klan shorthand for "A Klansman I Am." It is related to another Klan acronym, AYAK ("Are You A Klansman?"). These are among the many acronyms developed by the Second Ku Klux Klan that emerged in 1915. Although the Second Ku Klux Klan did not survive, much of its terminology and many of its rituals did, and later Klan groups freely used them. | G41: https://www.adl.org/resources/hate-symbol/akia | H41: https://www.adl.org/resources/hate-symbol/akia | J41: Marilyn | K41: low | L41: in HATE SYMBOLS DATABASE (or add)
A42: 39 | B42: Anti Racist is Code for Anti White | C42: https://extremismterms.adl.org/glossary/anti-racist-code-anti-white | D42: Slogans / Code words | E42: White supremacist, Right-wing, Antisemitism | F42: "Anti-racist is code for anti-white" is a white supremacist slogan used as a response to accusations of racism and to re-focus attention on the putative victimhood of the white race. | H42: https://www.adl.org/resources/hate-symbol/anti-racist-code-anti-white
A43: 41 | B43: Anti-Antifa | C43: https://extremismterms.adl.org/glossary/anti-antifa | D43: Slogans / Code words | E43: White supremacist, Right-wing, Antisemitism | F43: White supremacists coined the term "anti-antifa" and related imagery to express their disdain for anti-fascists. The term is used widely among right-wing extremists. | G43: https://www.adl.org/resources/hate-symbol/anti-antifa-images | H43: https://www.adl.org/resources/hate-symbol/anti-antifa-images
A44: 66 | B44: AYAK | C44: https://extremismterms.adl.org/glossary/ayak | D44: Slogans / Code words | E44: White supremacist, Right-wing, Antisemitism | F44: AYAK is an acronym that means "Are You A Klansmen." It is similar to the acronym AKIA, "A Klansman I Am." | G44: https://www.adl.org/resources/hate-symbol/ayak | H44: https://www.adl.org/resources/hate-symbol/ayak | K44: low | L44: in HATE SYMBOLS DATABASE (or add)
A45: 75 | B45: Blood and Soil | C45: https://extremismterms.adl.org/glossary/blood-and-soil | D45: Slogans / Code words | E45: White supremacist, Right-wing, Antisemitism | F45: "Blood and Soil" is a phrase that is a derivative of "Blut und Ehre" a slogan popularized by the Nazi Party in World War II. The phrase became the slogan for Vanguard America, romanticizing the notion that people with "white blood" have a special bond with the "American soil." | G45: https://www.adl.org/resources/hate-symbol/blut-und-ehre | H45: https://www.adl.org/resources/hate-symbol/blut-und-ehre | K45: low | L45: in HATE SYMBOLS DATABASE (or add)
A46: 628 | B46: Blut und Ehre | C46: https://extremismterms.adl.org/glossary/blut-und-ehre | D46: Slogans / Code words | E46: White supremacist, Right-wing, Antisemitism | F46: "Blut und Ehre" is a German phrase that translates into "Blood and Honor;" it was popularized by the Nazi Party (as a Hitler Youth slogan and elsewhere). Since World War II, this German phrase (and even more so its English translation) has commonly been used by white supremacists in Europe, the United States and elsewhere. | G46: https://www.adl.org/resources/hate-symbol/blut-und-ehre | H46: https://www.adl.org/resources/hate-symbol/blut-und-ehre | K46: low | L46: in HATE SYMBOLS DATABASE (or add)
A47: 128 | B47: Crazy White Boy | C47: https://extremismterms.adl.org/glossary/crazy-white-boy | D47: Slogans / Code words | E47: White supremacist, Right-wing, Antisemitism | G47: https://www.adl.org/resources/report/white-supremacist-prison-gangs-2022-assessment | H47: https://www.adl.org/resources/report/white-supremacist-prison-gangs-2022-assessment | K47: low | L47: in HATE SYMBOLS DATABASE (or add)
A48: 133 | B48: Cuckservatives | C48: https://extremismterms.adl.org/glossary/cuckservatives | D48: Slogans / Code words | E48: White supremacist, Right-wing, Antisemitism | F48: In 2015, alt right white supremacists began disparaging members of the conservative movement with the derogatory term "cuckservative," a com¬≠bi¬≠na¬≠tion of "con¬≠ser¬≠v¬≠a¬≠tive" and "cuck¬≠old," to describe a white con¬≠ser¬≠v¬≠a¬≠tive who putatively pro¬≠motes the inter¬≠ests of Jews and non-whites over those of whites. The Groypers, a group that attracts white supremacists and other far-right activists, also employ the term.
A49: 134 | B49: Da Goyim Know | C49: https://extremismterms.adl.org/glossary/da-goyim-know | D49: Slogans / Code words | E49: White supremacist, Right-wing, Antisemitism | F49: "Da Goyim Know" is an antisemitic catchphrase used to say that non-Jews have "figured out" an alleged Jewish conspiracy or plot, which therefore needs to be "shut down." Goyim is a pejorative term for non-Jews, used, in this case, by non-Jews themselves. It is most often associated with the alt right segment of the white supremacist movement, and message boards such as 4chan and 8chan. Antisemites use this phrase when pointing out alleged Jewish misdeeds. | G49: https://www.adl.org/resources/hate-symbol/goyim-knowshut-it-down | H49: https://www.adl.org/resources/hate-symbol/goyim-knowshut-it-down | K49: priority | L49: add to innocuous phrase article
A50: 145 | B50: Diversity = White Genocide (symbol) | C50: https://extremismterms.adl.org/glossary/diversity-white-genocide-symbol | D50: Slogans / Code words | E50: White supremacist, Right-wing, Antisemitism | F50: "Diversity = White Genocide" is a white supremacist slogan intended to suggest that multiculturalism will mean the death of the white race. | K50: low | L50: in HATE SYMBOLS DATABASE (or add)
A51: 171 | B51: Featherwood | C51: https://extremismterms.adl.org/glossary/featherwood | D51: Slogans / Code words | E51: White supremacist, Right-wing, Antisemitism | F51: Featherwood is a word deriving from the related term "peckerwood." It refers to a woman belonging to or associating with the white supremacist prison gang subculture or, primarily in California, with peckerwood street gangs. Featherwoods are frequently identified by tattoos of the term "featherwood" or a feather by itself. | G51: https://www.adl.org/resources/hate-symbol/featherwood | H51: https://www.adl.org/resources/hate-symbol/featherwood | K51: low | L51: in HATE SYMBOLS DATABASE (or add)
A52: 174 | B52: FGRN | C52: https://extremismterms.adl.org/glossary/fgrn | D52: Slogans / Code words | E52: White supremacist, Right-wing, Antisemitism | F52: FGRN is a Ku Klux Klan acronym for "For God, Race and Nation," a common Klan slogan. | G52: https://www.adl.org/resources/hate-symbol/fgrn | H52: https://www.adl.org/resources/hate-symbol/fgrn | K52: low | L52: in HATE SYMBOLS DATABASE (or add)
A53: 177 | B53: Firm 22 | C53: https://extremismterms.adl.org/glossary/firm-22 | D53: Slogans / Code words | E53: White supremacist, Right-wing, Antisemitism | F53: Firm 22 is the name used by the Vinlanders Social Club, a racist skinhead gang, to refer to supporters and associates of the group who are not actually members, such as the wives and girlfriends of gang members (not allowed to become members) or males interested in becoming prospective members. The number 22 stands for the letter V, as V is the 22nd letter in the alphabet. It is similar in nature to the Crew 38 established by the Hammerskins. | G53: https://www.adl.org/resources/hate-symbol/firm-22 | H53: https://www.adl.org/resources/hate-symbol/firm-22 | K53: low | L53: in HATE SYMBOLS DATABASE (or add)
A54: 207 | B54: GTKRWN | C54: https://extremismterms.adl.org/glossary/gtkrwn | D54: Slogans / Code words | E54: White supremacist, Right-wing, Antisemitism | F54: GTKRWN is a white supremacist acronym for the racist and antisemitic slogan "Gas the Kikes; Race War Now." Occasionally, white supremacists may only use the first part of the acronym: "GTK." | G54: https://www.adl.org/resources/hate-symbol/gtkrwn | H54: https://www.adl.org/resources/hate-symbol/gtkrwn | K54: low | L54: in HATE SYMBOLS DATABASE (or add)
A55: 222 | B55: HFFH (symbol) | C55: https://extremismterms.adl.org/glossary/hffh-symbol | D55: Slogans / Code words | E55: White supremacist, Right-wing, Antisemitism | F55: HFFH is an acronym used by the Hammerskins, a large racist skinhead gang. It stands for "Hammerskins Forever, Forever Hammerskins," a format probably adopted from biker gangs. | G55: https://www.adl.org/resources/hate-symbol/hffh | H55: https://www.adl.org/resources/hate-symbol/hffh | K55: low | L55: in HATE SYMBOLS DATABASE (or add)
A56: 229 | B56: HSN (symbol) | C56: https://extremismterms.adl.org/glossary/hsn-symbol | D56: Slogans / Code words | E56: White supremacist, Right-wing, Antisemitism | F56: HSN is an acronym used by the Hammerskins, a large racist skinhead gang. It stands for "Hammerskin Nation," which is a collective reference to the various regional Hammerskin gangs such as the Confederate Hammerskins and the Northern Hammerskins. | G56: https://www.adl.org/resources/hate-symbol/hsn | H56: https://www.adl.org/resources/hate-symbol/hsn | K56: low | L56: in HATE SYMBOLS DATABASE (or add)
A57: 671 | B57: Iron pill | C57: https://extremismterms.adl.org/glossary/iron-pill | D57: Slogans / Code words | E57: White supremacist, Right-wing, Antisemitism | F57: The Iron Pill is an accelerationist white supremacist reference to working out in preparation for the impending race war. | G57: https://www.adl.org/resources/article/extremist-medicine-cabinet-guide-online-pills | H57: https://www.adl.org/resources/article/extremist-medicine-cabinet-guide-online-pills | I57: Y
A58: 258 | B58: It's Okay To Be White | C58: https://extremismterms.adl.org/glossary/its-okay-be-white | D58: Slogans / Code words | E58: White supremacist, Right-wing, Antisemitism | F58: The phrase "It"s Okay To Be White" (may be abbreviated as IOTBW) is a slogan popularized in late 2017 as a trolling campaign by members of the controversial discussion forum 4chan. The original idea behind the campaign was to choose an ostensibly innocuous and inoffensive slogan, put that slogan on fliers bereft of any other words or imagery, then place the fliers in public locations. Some white supremacists have promoted the campaign, often adding Internet links to white supremacist websites to the fliers or combining the phrase with white supremacist language or imagery. | G58: https://www.adl.org/resources/hate-symbol/its-okay-be-white | H58: https://www.adl.org/resources/hate-symbol/its-okay-be-white | K58: low | L58: in HATE SYMBOLS DATABASE (or add)
A59: 259 | B59: ITSUB (symbol) | C59: https://extremismterms.adl.org/glossary/itsub-symbol | D59: Slogans / Code words | E59: White supremacist, Right-wing, Antisemitism | F59: ITSUB is a Ku Klux Klan acronym for "In The Sacred Unfailing Being," a reference to God. It is one of many Klan acronyms created by the Second Ku Klux Klan that emerged in 1915. | G59: https://www.adl.org/resources/hate-symbol/itsub | H59: https://www.adl.org/resources/hate-symbol/itsub | K59: low | L59: in HATE SYMBOLS DATABASE (or add)
A60: 277 | B60: Jewish Question/JQ | C60: https://extremismterms.adl.org/glossary/jewish-questionjq | D60: Slogans / Code words | E60: White supremacist, Right-wing, Antisemitism | F60: The "Jewish question" is an idea that began circulating in the 1800s. Some European writers, philosophers and theologians claimed that Jewish presence in society was a problem that needed to be solved. The Holocaust was the result of the Nazi party's effort to achieve what it referred to as the "final solution to the Jewish question." Modern antisemites use the phrase and it's abbreviation "JQ" to state their antisemitic bonafides and to indicate they're aware of the problem as it persists today, according to them. | K60: priority | L60: antisemitic term/symbol/conspiracy
A61: 279 | B61: Jews Will Not Replace Us | C61: https://extremismterms.adl.org/glossary/jews-will-not-replace-us | D61: Slogans / Code words | E61: White supremacist, Right-wing, Antisemitism | F61: "Jews Will Not Replace Us" is a variant of the white supremacist slogan "You Will Not Replace Us," referencing the belief that the white race is in danger of extinction by a rising tide of non-whites who are controlled and manipulated by Jews. This phrase was shouted by marching white supremacists in 2017 during the torch-lit rally the night before the deadly Unite The Right rally in Charlottesville, Virginia. | G61: https://www.adl.org/resources/hate-symbol/you-will-not-replace-us | H61: https://www.adl.org/resources/hate-symbol/you-will-not-replace-us | K61: priority | L61: antisemitic term/symbol/conspiracy
A62: 294 | B62: KABARK (symbol) | C62: https://extremismterms.adl.org/glossary/kabark-symbol | D62: Slogans / Code words | E62: White supremacist, Right-wing, Antisemitism | F62: KABARK is a Ku Klux Klan acronym for "Konstantly Applied By All Regular Klansmen." Today, it is essentially meaningless and only used as a "sign-off" in online messages by Klan group members. | G62: https://www.adl.org/resources/hate-symbol/kabark | H62: https://www.adl.org/resources/hate-symbol/kabark | K62: low | L62: in HATE SYMBOLS DATABASE (or add)
A63: 304 | B63: KIGY (symbol) | C63: https://extremismterms.adl.org/glossary/kigy-symbol | D63: Slogans / Code words | E63: White supremacist, Right-wing, Antisemitism | F63: KIGY is Ku Klux Klan shorthand for "Klansman I Greet You." | G63: https://www.adl.org/resources/hate-symbol/kigy | H63: https://www.adl.org/resources/hate-symbol/kigy | K63: low | L63: in HATE SYMBOLS DATABASE (or add)
A64: 305 | B64: KLASP (symbol) | C64: https://extremismterms.adl.org/glossary/klasp-symbol | D64: Slogans / Code words | E64: White supremacist, Right-wing, Antisemitism | F64: KLASP is a Ku Klux Klan acronym for "Klannish Loyalty, A Sacred Principle." | G64: https://www.adl.org/resources/hate-symbol/klasp | H64: https://www.adl.org/resources/hate-symbol/klasp | K64: low | L64: in HATE SYMBOLS DATABASE (or add)
A65: 321 | B65: LOTIE | C65: https://extremismterms.adl.org/glossary/lotie | D65: Slogans / Code words | E65: White supremacist, Right-wing, Antisemitism | F65: LOTIE is a Ku Klux Klan abbreviation for "Lady Of The Invisible Empire," i.e., a female Klan member. | G65: https://www.adl.org/resources/hate-symbol/lotie | H65: https://www.adl.org/resources/hate-symbol/lotie | K65: low | L65: in HATE SYMBOLS DATABASE (or add)
A66: 324 | B66: Love Your Race | C66: https://extremismterms.adl.org/glossary/love-your-race | D66: Slogans / Code words | E66: White supremacist, Right-wing, Antisemitism | F66: "Love Your Race" is a white supremacist slogan originally popularized by the neo-Nazi National Alliance. In white supremacist literature and flyers, the phrase is often accompanied by an idealized image of a beautiful and/or maternal white woman. | G66: https://www.adl.org/resources/hate-symbol/love-your-race | H66: https://www.adl.org/resources/hate-symbol/love-your-race | K66: low | L66: in HATE SYMBOLS DATABASE (or add)
A67: 340 | B67: Meine Ehre Heisst Treue | C67: https://extremismterms.adl.org/glossary/meine-ehre-heisst-treue | D67: Slogans / Code words | E67: White supremacist, Right-wing, Antisemitism | F67: "Meine Ehre Heisst Treue" is a German phrase that translates roughly to "My Honor Is Loyalty." It was used as a motto of the Waffen SS in Nazi Germany; today, many neo-Nazis and other white supremacists around the world use this German phrase (or its English equivalent) as a hate slogan. | G67: https://www.adl.org/resources/hate-symbol/meine-ehre-heisst-treue | H67: https://www.adl.org/resources/hate-symbol/meine-ehre-heisst-treue | K67: low | L67: in HATE SYMBOLS DATABASE (or add)
A68: 351 | B68: MIOAK | C68: https://extremismterms.adl.org/glossary/mioak | D68: Slogans / Code words | E68: White supremacist, Right-wing, Antisemitism | F68: MIOAK is an acronym used by members of Ku Klux Klan groups; it stands for "Mystic Insignia of a Klansman." It is more commonly referred to as the "Blood Drop" Cross. See also: Blood Drop Cross | G68: https://www.adl.org/resources/hate-symbol/blood-drop-cross | H68: https://www.adl.org/resources/hate-symbol/blood-drop-cross | K68: low | L68: in HATE SYMBOLS DATABASE (or add)
A69: 357 | B69: Moon Man | C69: https://extremismterms.adl.org/glossary/moon-man | D69: Slogans / Code words | E69: White supremacist, Right-wing, Antisemitism | F69: "Moon Man" is a meme derived from a character in 1980s McDonald"s restaurant commercials. The charachter has been appropriated by white supremacists, especially from the alt right, who attach it to racist songs, language and imagery. | G69: https://www.adl.org/resources/hate-symbol/moon-man | H69: https://www.adl.org/resources/hate-symbol/moon-man | K69: low | L69: in HATE SYMBOLS DATABASE (or add)
A70: 389 | B70: Nihilism (Accelerationist) | C70: https://extremismterms.adl.org/glossary/nihilism-accelerationist | D70: Slogans / Code words | E70: White supremacist, Right-wing, Antisemitism | F70: The accelerationist interpretation of nihilism is that society is corrupt and otherwise beyond repair. It is central to the book Siege, by neo-Nazi James Mason, which argues that society is being manipulated by Jewish elites at the expense of the white race., and the only way the white race can survive is by destroying the current system and creating a white ethnostate. | G70: https://www.adl.org/resources/backgrounder/accelerationism | H70: https://www.adl.org/resources/backgrounder/accelerationism | I70: Y
A71: 391 | B71: No Political Solution | C71: https://extremismterms.adl.org/glossary/no-political-solution | D71: Slogans / Code words | E71: White supremacist, Right-wing, Antisemitism | F71: "No political solution" is a phrase often used by adherents of the accelerationist philosophy to emphasize that voting or other political means will not bring about the radical societal change that they seek. Therefore, violent means should be employed to accelerate the destruction of society as it currently stands so that a new world order will arise placing the white race at the top of the societal hierarchy. | G71: https://www.adl.org/resources/backgrounder/accelerationism | H71: https://www.adl.org/resources/backgrounder/accelerationism | I71: Y
A72: 393 | B72: Non Silba Sed Anthar | C72: https://extremismterms.adl.org/glossary/non-silba-sed-anthar | D72: Slogans / Code words | E72: White supremacist, Right-wing, Antisemitism | F72: "Non Silba Sed Anthar" is a Ku Klux Klan slogan meaning "Not Self, But Others." It is sometimes abbreviated as NSSA. | G72: https://www.adl.org/resources/hate-symbol/non-silba-sed-anthar | H72: https://www.adl.org/resources/hate-symbol/non-silba-sed-anthar
A73: 397 | B73: Northwest American Republic | C73: https://extremismterms.adl.org/glossary/northwest-american-republic | D73: Slogans / Code words | E73: White supremacist, Right-wing, Antisemitism | F73: The "Northwest American Republic" is a fictional construct created by Harold Covington (1953-2018), a long-time fringe figure in the neo-Nazi movement. It is based on the so-called "Northwest Imperative," a long-standing call by some white supremacists for white people to move to the Pacific Northwest and establish their own country. | G73: https://www.adl.org/resources/hate-symbol/northwest-american-republic | H73: https://www.adl.org/resources/hate-symbol/northwest-american-republic
A74: 398 | B74: Northwest Imperative | C74: https://extremismterms.adl.org/glossary/northwest-imperative | D74: Slogans / Code words | E74: White supremacist, Right-wing, Antisemitism | F74: Northwest Imperative is a long-standing call by some white supremacists for white people to move to the Pacific Northwest and establish their own country there. | G74: https://www.adl.org/resources/hate-symbol/northwest-american-republic | H74: https://www.adl.org/resources/hate-symbol/northwest-american-republic
A75: 707 | B75: ORION Symbol | C75: https://extremismterms.adl.org/glossary/orion-symbol | D75: Slogans / Code words | E75: White supremacist, Right-wing, Antisemitism | F75: "Our Race Is Our Nation" or "ORION" is a racist slogan proclaiming that racial ties are paramount to all else, transcending national borders or boundaries. Different white supremacists use the slogan, including Christian Identity adherents, neo-Nazis and the Klan. | G75: https://www.adl.org/resources/hate-symbol/orion | H75: https://www.adl.org/resources/hate-symbol/orion | K75: low | L75: in HATE SYMBOLS DATABASE (or add)
A76: 723 | B76: Peckerwood | C76: https://extremismterms.adl.org/glossary/peckerwood | D76: Slogans / Code words | E76: White supremacist, Right-wing, Antisemitism | F76: Peckerwood, derived from an old racial epithet aimed at whites, has evolved to become a term used to refer to white prisoners, particularly white prisoners belonging to the white supremacist prison gang subculture. Often the term is shortened to "wood" and all such prisoners in a particular prison might be referred to as the "woodpile." Female members or associates are referred to as featherwoods. | G76: https://www.adl.org/resources/hate-symbol/peckerwood | H76: https://www.adl.org/resources/hate-symbol/peckerwood | K76: low | L76: in HATE SYMBOLS DATABASE (or add)
A77: 425 | B77: ROA | C77: https://extremismterms.adl.org/glossary/roa | D77: Slogans / Code words | E77: White supremacist, Right-wing, Antisemitism | F77: ROA is an acronym for the white supremacist slogan "Race Over All," popularized by the neo-Nazi/racist skinhead gang Volksfront. | G77: https://www.adl.org/resources/hate-symbol/roa | H77: https://www.adl.org/resources/hate-symbol/roa | K77: low | L77: in HATE SYMBOLS DATABASE (or add)
A78: 429 | B78: Rock Against Communism (RAC) | C78: https://extremismterms.adl.org/glossary/rock-against-communism-rac | D78: Slogans / Code words | E78: White supremacist, Right-wing, Antisemitism | F78: Rock Against Communism (RAC) is a euphemism for several types of white supremacist hate music (typically Oi! or hatecore punk). The phrase "Rock Against ..." has become so popular among white supremacists that it's been appropriated and used in various other contexts such as "Rock Against Coronavirus" and "Rock Against Islam." | G78: https://www.adl.org/resources/hate-symbol/rock-against-communism | H78: https://www.adl.org/resources/hate-symbol/rock-against-communism | K78: low | L78: in HATE SYMBOLS DATABASE (or add)
A79: 442 | B79: Sieg Heil symbol | C79: https://extremismterms.adl.org/glossary/sieg-heil-symbol | D79: Slogans / Code words | E79: White supremacist, Right-wing, Antisemitism | F79: "Sieg Heil" is a German phrase that translates to "Hail Victory." The phrase became one of the German Nazi Party's most widely used and notorious slogans. Following World War II, white supremacists worldwide also adopted the phrase. | G79: https://www.adl.org/resources/hate-symbol/sieg-heil | H79: https://www.adl.org/resources/hate-symbol/sieg-heil | K79: low | L79: in HATE SYMBOLS DATABASE (or add)
A80: 444 | B80: Siege pill | C80: https://extremismterms.adl.org/glossary/siege-pill | D80: Slogans / Code words | E80: White supremacist, Right-wing, Antisemitism | F80: "Siege pill" is used by followers of the philosophy of accelerationism to describe someone who has read and understands neo-Nazi James Mason's Siege essays, which are foundational to accelerationist philosophy. | G80: https://www.adl.org/resources/article/extremist-medicine-cabinet-guide-online-pills | H80: https://www.adl.org/resources/article/extremist-medicine-cabinet-guide-online-pills | I80: Y | K80: low | L80: in HATE SYMBOLS DATABASE (or add)
A81: 445 | B81: Siegeculture | C81: https://extremismterms.adl.org/glossary/siegeculture | D81: Slogans / Code words | E81: White supremacist, Right-wing, Antisemitism | F81: Siegeculture, also known as Siegekultur, is a philosophy, political orientation, spiritual outlook and solution to societal problems dominated by hate and an embrace of violence anchored in fascist ideology and accelerationism. It draws on the teachings and actions of James Mason, Adolf Hitler and Charles Manson, among others. | G81: https://www.adl.org/resources/backgrounder/accelerationism | H81: https://www.adl.org/resources/backgrounder/accelerationism | I81: Y | J81: We could use a "glossary of terms" addition to this resource | K81: low | L81: in HATE SYMBOLS DATABASE (or add)
A82: 464 | B82: SWP | C82: https://extremismterms.adl.org/glossary/swp | D82: Slogans / Code words | E82: White supremacist, Right-wing, Antisemitism | F82: SWP is an acronym for the white supremacist slogan "Supreme White Power." It seems to have originated on the West Coast, probably in California's prison system, though it has spread from there. | G82: https://www.adl.org/resources/hate-symbol/swp | H82: https://www.adl.org/resources/hate-symbol/swp | K82: low | L82: in HATE SYMBOLS DATABASE (or add)
A83: 516 | B83: Universal Order | C83: https://extremismterms.adl.org/glossary/universal-order | D83: Slogans / Code words | E83: White supremacist, Right-wing, Antisemitism | F83: Universal Order is a concept that was created by James Mason, articulated in his neo-Nazi compilation of essays, Siege. Universal Order states that there is one inherent truth that races are unequal and social conflict arises from not understanding this truth. According to Mason, the white race exists at the top of this racial hierarchy, and therefore, the domination of the white race would fulfill this truth. | K83: low | L83: in HATE SYMBOLS DATABASE (or add)
A84: 846 | B84: White Lives Matter | C84: https://extremismterms.adl.org/glossary/white-lives-matter | D84: Slogans / Code words | E84: White supremacist, Right-wing, Antisemitism | F84: "White Lives Matter" is a white supremacist phrase that originated in early 2015 as a racist response to the Black Lives Matter movement, which arose to protest police brutality against African Americans and garnered considerable publicity in 2014 for protests in Ferguson, Missouri following the shooting death of Michael Brown at the hands of a Ferguson police officer. | G84: https://adl.org/resources/backgrounder/white-lives-matter | H84: https://adl.org/resources/backgrounder/white-lives-matter | I84: Y | K84: low | L84: in HATE SYMBOLS DATABASE (or add)
A85: 849 | B85: White Power | C85: https://extremismterms.adl.org/glossary/white-power | D85: Slogans / Code words | E85: White supremacist, Right-wing, Antisemitism | F85: "White Power" is a white supremacist slogan designed to mimic the "black power" slogan often used by African Americans in the 1960s/70s. It is commonly shouted at white supremacist events as a racist rallying cry. | K85: low | L85: in HATE SYMBOLS DATABASE (or add)
A86: 851 | B86: White Pride Worldwide (WPWW) | C86: https://extremismterms.adl.org/glossary/white-pride-worldwide-wpww | D86: Slogans / Code words | E86: White supremacist, Right-wing, Antisemitism | F86: WPWW is a common white supremacist acronym that stands for "White Pride World Wide." The phrase is used as part of the logo for Stormfront, the largest white supremacist website on the internet, which accounts for its widespread use by white supremacists. | K86: low | L86: in HATE SYMBOLS DATABASE (or add)
A87: 852 | B87: White Rex Clothing | C87: https://extremismterms.adl.org/glossary/white-rex-clothing | D87: Slogans / Code words | E87: White supremacist, Right-wing, Antisemitism | F87: White Rex Clothing is a white supremacist clothing company based in Russia founded by Denis Nikitin. The brand is popular among neo-Nazi MMA fight clubs and has hosted amateur MMA tournaments in Europe. | K87: low | L87: in HATE SYMBOLS DATABASE (or add)
A88: 538 | B88: WP | C88: https://extremismterms.adl.org/glossary/wp | D88: Slogans / Code words | E88: White supremacist, Right-wing, Antisemitism | F88: WP is an acronym for the common white supremacist chant "White Power." In some contexts, WP may refer to "White Pride" instead. | G88: https://www.adl.org/resources/hate-symbol/wp | H88: https://www.adl.org/resources/hate-symbol/wp | I88: Y | K88: low | L88: in HATE SYMBOLS DATABASE (or add)
A89: 540 | B89: Zyklon B | C89: https://extremismterms.adl.org/glossary/zyklon-b | D89: Slogans / Code words | E89: White supremacist, Right-wing, Antisemitism | F89: Zyklon B was the name of the gas used to murder more than one million people, most of them Jews, in the death camps constructed by Nazi Germany during the Holocaust. Because of its association with killing Jews, Zyklon B has been adopted as a symbol by modern-day white supremacists, who often use it to spread antisemitic content. | G89: https://www.adl.org/resources/hate-symbol/zyklon-b | H89: https://www.adl.org/resources/hate-symbol/zyklon-b | I89: Y | K89: priority | L89: antisemitic term/symbol/conspiracy
A90: 578 | B90: 5 Words | C90: https://extremismterms.adl.org/glossary/5-words | D90: Slogans / Code words | E90: White supremacist, Right-wing | F90: The 5 words refer to the phrase "I have nothing to say," which is what some white supremacists believe should be the only words shared with police. | G90: https://www.adl.org/resources/hate-symbol/5-words | H90: https://www.adl.org/resources/hate-symbol/5-words | J90: Marilyn | K90: low | L90: in HATE SYMBOLS DATABASE (or add)
A91: 836 | B91: VaxTheBlacks | C91: https://extremismterms.adl.org/glossary/vaxtheblacks | D91: Slogans / Code words | E91: White supremacist, Right-wing | F91: VaxTheBlacks is a white supremacist idea and online campaign that began during the COVID-19 pandemic. It promoted the idea that because the vaccine is allegedly harmful, black people should receive it first in the hope it could make the community infertile and slow down a perceived white genocide. | K91: priority | L91: add to innocuous phrase article
A92: 283 | B92: Jogger | C92: https://extremismterms.adl.org/glossary/jogger | D92: Slogans / Code words | E92: White supremacist | F92: Coined in 2020, a white supremacist term for a Black man references Ahmaud Arbery, who was murdered while jogging in his Georgia neighborhood. | K92: low | L92: in HATE SYMBOLS DATABASE (or add)
A93: 68722 | B93: "Gender Ideology" | C93: https://extremismterms.adl.org/glossary/gender-ideology | D93: Slogans / Code words | E93: Single-issue | F93: ‚ÄúGender ideology‚Äù (also known as ‚ÄúLGBTQ+ ideology‚Äù) is a conspiratorial phrase coined by anti-LGBTQ+ activists and extremists to characterize attempts to achieve LGBTQ+ rights or representation as an extreme ideology or even part of a nefarious left-wing plot to dominate public institutions. Proponents of the phrase often use it to oppose school curricula that feature and/or celebrate LGBTQ+ history or experiences, falsely claiming that such materials promote the sexualization of minors and/or coerce children into identifying as members of the LGBTQ+ community. Anti-LGBTQ+ activists also use the term in legal and political contexts to defend or rationalize their opposition to LGBTQ+ rights. | G93: https://www.adl.org/resources/article/online-amplifiers-anti-lgbtq-extremism | H93: https://www.adl.org/resources/article/online-amplifiers-anti-lgbtq-extremism | J93: Marilyn
A94: 35 | B94: Anchor Baby | C94: https://extremismterms.adl.org/glossary/anchor-baby | D94: Slogans / Code words | E94: Single-issue | F94: Anchor baby is a derogatory term for a child born in the United States to an undocumented immigrant. Since these children automatically qualify as American citizens, they can later act as a sponsor for other family members.
A95: 148 | B95: Dog pill | C95: https://extremismterms.adl.org/glossary/dog-pill | D95: Slogans / Code words | E95: Single-issue | F95: The "dog pill" refers to the belief among some incels that women would rather sleep with dogs than with them. | G95: https://www.adl.org/resources/article/extremist-medicine-cabinet-guide-online-pills | H95: https://www.adl.org/resources/article/extremist-medicine-cabinet-guide-online-pills | I95: Y
A96: 179 | B96: Foid | C96: https://extremismterms.adl.org/glossary/foid | D96: Slogans / Code words | E96: Single-issue | F96: Foid is a derogatory incel term for woman. The phrase is an abbreviation of "femoid" which combines the words "female" and "humanoid" or "female" and "android." Incels attribute their virgin status to "heartless" females and their rage leads them dehumanize and even murder women. | G96: https://www.adl.org/resources/backgrounder/incels-involuntary-celibates | H96: https://www.adl.org/resources/backgrounder/incels-involuntary-celibates | I96: Y | K96: low | L96: Incel/ misogyny terms/phrases
A97: 195 | B97: Going ER | C97: https://extremismterms.adl.org/glossary/going-er | D97: Slogans / Code words | E97: Single-issue | F97: "Going ER" is a reference to Elliot Rodger, a violent incel who committed mass murder in Santa Barbara, California in 2014. Prior to the shooting, Rodger wrote an angry manifesto blaming women for rejecting him. "Going ER" refers to the act of committing mass murder, as inspired by Rodger. | G97: https://www.adl.org/resources/backgrounder/incels-involuntary-celibates | H97: https://www.adl.org/resources/backgrounder/incels-involuntary-celibates | I97: Y
A98: 232 | B98: Hypergamy | C98: https://extremismterms.adl.org/glossary/hypergamy | D98: Slogans / Code words | E98: Single-issue | F98: Hypergamy is a term incels use for the belief that women seek out men who are of higher status " either physically or financially " over other men. | G98: https://www.adl.org/resources/backgrounder/incels-involuntary-celibates | H98: https://www.adl.org/resources/backgrounder/incels-involuntary-celibates | I98: Y
A99: 672 | B99: JB pill | C99: https://extremismterms.adl.org/glossary/jb-pill | D99: Slogans / Code words | E99: Single-issue | F99: JB pill stands for "jail bait" and is a reference to pedophilia. | G99: https://www.adl.org/resources/article/extremist-medicine-cabinet-guide-online-pills | H99: https://www.adl.org/resources/article/extremist-medicine-cabinet-guide-online-pills | I99: Y
A100: 698 | B100: Normie | C100: https://extremismterms.adl.org/glossary/normie | D100: Slogans / Code words | E100: Single-issue | F100: In the incel community, a "normie" is a someone of average attractiveness and/or intelligence. "Normies" are viewed by incels as superior and in the incel hierarchy, "Normies" fall between "Chads" and "incels." | G100: https://www.adl.org/resources/backgrounder/incels-involuntary-celibates | H100: https://www.adl.org/resources/backgrounder/incels-involuntary-celibates | I100: Y
...
